<?xml version='1.0' encoding='ISO-8859-1'?>
<PropertyList>
  <runway>
    <threshold>
      <lon>-75.17470082</lon>
      <lat>43.02249079</lat>
      <rwy>13</rwy>
      <hdg-deg>117.00</hdg-deg>
      <displ-m>0.0</displ-m>
      <stopw-m>0.0</stopw-m>
    </threshold>
    <threshold>
      <lon>-75.16617642</lon>
      <lat>43.01931531</lat>
      <rwy>31</rwy>
      <hdg-deg>297.00</hdg-deg>
      <displ-m>0.0</displ-m>
      <stopw-m>0.0</stopw-m>
    </threshold>
  </runway>
</PropertyList>
