<?xml version='1.0' encoding='ISO-8859-1'?>
<PropertyList>
  <runway>
    <threshold>
      <lon>-83.77819949</lon>
      <lat>35.81052052</lat>
      <rwy>07</rwy>
      <hdg-deg>67.00</hdg-deg>
      <displ-m>0.0</displ-m>
      <stopw-m>0.0</stopw-m>
    </threshold>
    <threshold>
      <lon>-83.77103829</lon>
      <lat>35.81298558</lat>
      <rwy>25</rwy>
      <hdg-deg>247.00</hdg-deg>
      <displ-m>0.0</displ-m>
      <stopw-m>0.0</stopw-m>
    </threshold>
  </runway>
</PropertyList>
