<?xml version="1.0"?>
<groundnet>
  <version>1</version>
  <parkingList>
        <Parking index="0" type="gate" name="32_(Terminal_Apron)" lat="N60 17.402109" lon="E5 13.693830" heading="210.57"  radius="20" pushBackRoute="98" airlineCodes="" />
        <Parking index="1" type="gate" name="31_(Terminal_Apron)" lat="N60 17.405126" lon="E5 13.635328" heading="181.71"  radius="20" pushBackRoute="101" airlineCodes="" />
        <Parking index="2" type="gate" name="29_(Terminal_Apron)" lat="N60 17.400014" lon="E5 13.582379" heading="155.8"  radius="20" pushBackRoute="155" airlineCodes="" />
        <Parking index="3" type="gate" name="28_(Terminal_Apron)" lat="N60 17.384843" lon="E5 13.538548" heading="131.58"  radius="36" pushBackRoute="153" airlineCodes="" />
        <Parking index="4" type="gate" name="27_(Terminal_Apron)" lat="N60 17.359081" lon="E5 13.521369" heading="106.98"  radius="20" pushBackRoute="88" airlineCodes="" />
        <Parking index="5" type="gate" name="26_(Terminal_Apron)" lat="N60 17.333322" lon="E5 13.513466" heading="82.75"  radius="20" pushBackRoute="87" airlineCodes="" />
        <Parking index="6" type="gate" name="25_(Terminal_Apron)" lat="N60 17.308473" lon="E5 13.527106" heading="59.84"  radius="20" pushBackRoute="86" airlineCodes="" />
        <Parking index="7" type="gate" name="24_(Terminal_Apron)" lat="N60 17.285795" lon="E5 13.560901" heading="33.95"  radius="36" pushBackRoute="82" airlineCodes="" />
        <Parking index="8" type="gate" name="23_(Terminal_Apron)" lat="N60 17.277600" lon="E5 13.612046" heading="9.39"  radius="20" pushBackRoute="161" airlineCodes="" />
        <Parking index="9" type="gate" name="22_(Terminal_Apron)" lat="N60 17.282457" lon="E5 13.665500" heading="342.58"  radius="20" pushBackRoute="162" airlineCodes="" />
        <Parking index="10" type="gate" name="21_(Terminal_Apron)" lat="N60 17.291760" lon="E5 13.719634" heading="318.17"  radius="20" pushBackRoute="85" airlineCodes="" />
        <Parking index="11" type="ga" name="H56_(Heli_Apron)" lat="N60 17.589837" lon="E5 13.424478" heading="350.6"  radius="18" pushBackRoute="67" airlineCodes="" />
        <Parking index="12" type="ga" name="H55_(Heli_Apron)" lat="N60 17.570170" lon="E5 13.431149" heading="350.6"  radius="18" pushBackRoute="66" airlineCodes="" />
        <Parking index="13" type="ga" name="H54_(Heli_Apron)" lat="N60 17.550573" lon="E5 13.437715" heading="350.6"  radius="18" pushBackRoute="65" airlineCodes="" />
        <Parking index="14" type="ga" name="H53_(Heli_Apron)" lat="N60 17.530944" lon="E5 13.444420" heading="350.6"  radius="18" pushBackRoute="64" airlineCodes="" />
        <Parking index="15" type="ga" name="H52_(Heli_Apron)" lat="N60 17.511293" lon="E5 13.450950" heading="350.6"  radius="18" pushBackRoute="63" airlineCodes="" />
        <Parking index="16" type="ga" name="H51_(Heli_Apron)" lat="N60 17.491713" lon="E5 13.457479" heading="350.6"  radius="18" pushBackRoute="62" airlineCodes="" />
        <Parking index="17" type="ga" name="H50_(Heli_Apron)" lat="N60 17.471996" lon="E5 13.464089" heading="350.6"  radius="18" pushBackRoute="96" airlineCodes="" />
        <Parking index="18" type="gate" name="48_(Apron_N)" lat="N60 17.441333" lon="E5 13.472455" heading="55.38"  radius="20" pushBackRoute="152" airlineCodes="" />
        <Parking index="19" type="gate" name="47_(Apron_N)" lat="N60 17.437352" lon="E5 13.525021" heading="27.14"  radius="20" pushBackRoute="153" airlineCodes="" />
        <Parking index="20" type="gate" name="46_(Apron_N)" lat="N60 17.441863" lon="E5 13.580668" heading="10.89"  radius="20" pushBackRoute="155" airlineCodes="" />
        <Parking index="21" type="gate" name="43_(Apron_N)" lat="N60 17.443528" lon="E5 13.636290" heading="358.04"  radius="20" pushBackRoute="101" airlineCodes="" />
        <Parking index="22" type="gate" name="42_(Apron_N)" lat="N60 17.459169" lon="E5 13.686149" heading="84.23"  radius="20" pushBackRoute="92" airlineCodes="" />
        <Parking index="23" type="gate" name="8_(Remote_Apron_S)" lat="N60 17.137797" lon="E5 13.593025" heading="81.18"  radius="20" pushBackRoute="79" airlineCodes="" />
        <Parking index="24" type="gate" name="7_(Remote_Apron_S)" lat="N60 17.114786" lon="E5 13.593237" heading="80.74"  radius="20" pushBackRoute="78" airlineCodes="" />
        <Parking index="25" type="gate" name="6_(Remote_Apron_S)" lat="N60 17.089772" lon="E5 13.601282" heading="80.91"  radius="20" pushBackRoute="77" airlineCodes="" />
        <Parking index="26" type="gate" name="5_(Remote_Apron_S)" lat="N60 17.063973" lon="E5 13.586400" heading="80.5"  radius="20" pushBackRoute="167" airlineCodes="" />
        <Parking index="27" type="gate" name="4_(Remote_Apron_S)" lat="N60 17.042109" lon="E5 13.585321" heading="95.92"  radius="20" pushBackRoute="168" airlineCodes="" />
        <Parking index="28" type="gate" name="3_(Remote_Apron_S)" lat="N60 17.017172" lon="E5 13.595035" heading="90"  radius="20" pushBackRoute="169" airlineCodes="" />
        <Parking index="29" type="gate" name="2_(Remote_Apron_S)" lat="N60 16.991507" lon="E5 13.599800" heading="84.26"  radius="20" pushBackRoute="71" airlineCodes="" />
        <Parking index="30" type="gate" name="1L_(Remote_Apron_S)" lat="N60 16.971624" lon="E5 13.609349" heading="131.31"  radius="20" pushBackRoute="73" airlineCodes="" />
        <Parking index="31" type="gate" name="1R_(Remote_Apron_S)" lat="N60 16.942801" lon="E5 13.601144" heading="131.16"  radius="20" pushBackRoute="70" airlineCodes="" />
        <Parking index="32" type="gate" name="1_(Remote_Apron_S)" lat="N60 16.959076" lon="E5 13.603672" heading="204.63"  radius="36" pushBackRoute="72" airlineCodes="" />
        <Parking index="33" type="gate" name="60_(Hangar)" lat="N60 17.662789" lon="E5 13.502874" heading="358.73"  radius="20" pushBackRoute="104" airlineCodes="" />
        <Parking index="34" type="ga" name="GA_14_(Remote_Apron_N)" lat="N60 18.155315" lon="E5 13.815304" heading="-100.81"  radius="18" pushBackRoute="102" airlineCodes="" />
        <Parking index="35" type="ga" name="GA_13_(Remote_Apron_N)" lat="N60 18.162196" lon="E5 13.803122" heading="-108.08"  radius="18" pushBackRoute="102" airlineCodes="" />
        <Parking index="36" type="ga" name="GA_12_(Remote_Apron_N)" lat="N60 18.086260" lon="E5 13.664837" heading="-146.73"  radius="18" pushBackRoute="120" airlineCodes="" />
        <Parking index="37" type="ga" name="GA_11_(Remote_Apron_N)" lat="N60 18.072542" lon="E5 13.652212" heading="9.24"  radius="18" pushBackRoute="103" airlineCodes="" />
        <Parking index="38" type="ga" name="GA_10_(Remote_Apron_N)" lat="N60 18.078523" lon="E5 13.637261" heading="71.2"  radius="18" pushBackRoute="103" airlineCodes="" />
        <Parking index="39" type="ga" name="GA_9_(Remote_Apron_N)" lat="N60 18.087742" lon="E5 13.645367" heading="158.99"  radius="18" pushBackRoute="116" airlineCodes="" />
        <Parking index="40" type="ga" name="GA_8_(Remote_Apron_N)" lat="N60 18.050452" lon="E5 13.753091" heading="-89.92"  radius="18" pushBackRoute="114" airlineCodes="" />
        <Parking index="41" type="ga" name="GA_7_(Remote_Apron_N)" lat="N60 18.042234" lon="E5 13.754340" heading="-89.92"  radius="18" pushBackRoute="115" airlineCodes="" />
        <Parking index="42" type="ga" name="GA_6_(Remote_Apron_N)" lat="N60 18.032426" lon="E5 13.753270" heading="281.82"  radius="18" pushBackRoute="115" airlineCodes="" />
        <Parking index="43" type="ga" name="GA_5_(Remote_Apron_N)" lat="N60 18.034458" lon="E5 13.695662" heading="-258.94"  radius="18" pushBackRoute="122" airlineCodes="" />
        <Parking index="44" type="ga" name="GA_4_(Remote_Apron_N)" lat="N60 18.058899" lon="E5 13.631332" heading="184.32"  radius="18" pushBackRoute="116" airlineCodes="" />
        <Parking index="45" type="ga" name="GA_3_(Remote_Apron_N)" lat="N60 18.059571" lon="E5 13.611461" heading="127.81"  radius="18" pushBackRoute="103" airlineCodes="" />
        <Parking index="46" type="ga" name="GA_2_(Remote_Apron_N)" lat="N60 18.045440" lon="E5 13.624207" heading="-10.72"  radius="18" pushBackRoute="123" airlineCodes="" />
        <Parking index="47" type="ga" name="GA_1_(Remote_Apron_N)" lat="N60 18.049830" lon="E5 13.607153" heading="58.66"  radius="18" pushBackRoute="103" airlineCodes="" />
        <Parking index="48" type="ga" name="GA_9_(Technical_Apron)" lat="N60 17.731414" lon="E5 13.589671" heading="-90.08"  radius="18" pushBackRoute="110" airlineCodes="" />
        <Parking index="49" type="ga" name="GA_8_(Technical_Apron)" lat="N60 17.722409" lon="E5 13.589437" heading="-90.08"  radius="18" pushBackRoute="110" airlineCodes="" />
        <Parking index="50" type="ga" name="GA_7_(Technical_Apron)" lat="N60 17.712636" lon="E5 13.590235" heading="-90.08"  radius="18" pushBackRoute="110" airlineCodes="" />
        <Parking index="51" type="ga" name="GA_6_(Technical_Apron)" lat="N60 17.703096" lon="E5 13.587934" heading="-90.08"  radius="18" pushBackRoute="110" airlineCodes="" />
        <Parking index="52" type="ga" name="GA_5_(Technical_Apron)" lat="N60 17.693323" lon="E5 13.588826" heading="-90.08"  radius="18" pushBackRoute="110" airlineCodes="" />
        <Parking index="53" type="ga" name="GA_4_(Technical_Apron)" lat="N60 17.672326" lon="E5 13.593610" heading="-98.41"  radius="18" pushBackRoute="111" airlineCodes="" />
        <Parking index="54" type="ga" name="GA_3_(Technical_Apron)" lat="N60 17.664586" lon="E5 13.598242" heading="-98.41"  radius="18" pushBackRoute="112" airlineCodes="" />
        <Parking index="55" type="ga" name="GA_2_(Technical_Apron)" lat="N60 17.652464" lon="E5 13.584032" heading="330.89"  radius="18" pushBackRoute="112" airlineCodes="" />
        <Parking index="56" type="ga" name="GA_1_(Technical_Apron)" lat="N60 17.651977" lon="E5 13.562680" heading="331.53"  radius="18" pushBackRoute="112" airlineCodes="" />
        <Parking index="57" type="ga" name="GA_0_(Technical_Apron)" lat="N60 17.674479" lon="E5 13.553785" heading="-92.98"  radius="18" pushBackRoute="111" airlineCodes="" />
        <Parking index="58" type="gate" name="PAD_4_(DE-ICE)" lat="N60 17.811885" lon="E5 13.372310" heading="260.39"  radius="20" pushBackRoute="137" airlineCodes="" />
        <Parking index="59" type="gate" name="PAD_3_(DE-ICE)" lat="N60 17.796945" lon="E5 13.369477" heading="260.6"  radius="36" pushBackRoute="139" airlineCodes="" />
        <Parking index="60" type="gate" name="PAD_2_(DE-ICE)" lat="N60 17.788516" lon="E5 13.379839" heading="260.5"  radius="20" pushBackRoute="139" airlineCodes="" />
        <Parking index="61" type="gate" name="PAD_1_(DE-ICE)" lat="N60 17.763311" lon="E5 13.388015" heading="260.49"  radius="20" pushBackRoute="140" airlineCodes="" />
 </parkingList>
 <TaxiNodes>
        <node index="62" lat="N60 17.471107" lon="E5 13.453048" isOnRunway="0" holdPointType="PushBack"  />
        <node index="63" lat="N60 17.490697" lon="E5 13.445888" isOnRunway="0" holdPointType="PushBack"  />
        <node index="64" lat="N60 17.510238" lon="E5 13.438532" isOnRunway="0" holdPointType="PushBack"  />
        <node index="65" lat="N60 17.529828" lon="E5 13.431470" isOnRunway="0" holdPointType="PushBack"  />
        <node index="66" lat="N60 17.549466" lon="E5 13.424113" isOnRunway="0" holdPointType="PushBack"  />
        <node index="67" lat="N60 17.569105" lon="E5 13.418817" isOnRunway="0" holdPointType="PushBack"  />
        <node index="68" lat="N60 17.588889" lon="E5 13.413520" isOnRunway="0" holdPointType="none"  />
        <node index="69" lat="N60 16.940912" lon="E5 13.599233" isOnRunway="0" holdPointType="none"  />
        <node index="70" lat="N60 16.952087" lon="E5 13.573367" isOnRunway="0" holdPointType="PushBack"  />
        <node index="71" lat="N60 16.983143" lon="E5 13.563045" isOnRunway="0" holdPointType="PushBack"  />
        <node index="72" lat="N60 16.967827" lon="E5 13.611103" isOnRunway="0" holdPointType="PushBack"  />
        <node index="73" lat="N60 16.991717" lon="E5 13.594982" isOnRunway="0" holdPointType="PushBack"  />
        <node index="74" lat="N60 17.017237" lon="E5 13.593311" isOnRunway="0" holdPointType="none"  />
        <node index="75" lat="N60 17.041628" lon="E5 13.585480" isOnRunway="0" holdPointType="none"  />
        <node index="76" lat="N60 17.064596" lon="E5 13.585610" isOnRunway="0" holdPointType="none"  />
        <node index="77" lat="N60 17.089894" lon="E5 13.595661" isOnRunway="0" holdPointType="PushBack"  />
        <node index="78" lat="N60 17.115127" lon="E5 13.589657" isOnRunway="0" holdPointType="PushBack"  />
        <node index="79" lat="N60 17.138161" lon="E5 13.589135" isOnRunway="0" holdPointType="PushBack"  />
        <node index="80" lat="N60 17.285932" lon="E5 13.665791" isOnRunway="0" holdPointType="none"  />
        <node index="81" lat="N60 17.284198" lon="E5 13.612786" isOnRunway="0" holdPointType="none"  />
        <node index="82" lat="N60 17.289266" lon="E5 13.560592" isOnRunway="0" holdPointType="PushBack"  />
        <node index="83" lat="N60 17.296671" lon="E5 13.716748" isOnRunway="0" holdPointType="none"  />
        <node index="84" lat="N60 17.289293" lon="E5 13.730159" isOnRunway="0" holdPointType="none"  />
        <node index="85" lat="N60 17.257054" lon="E5 13.734467" isOnRunway="0" holdPointType="PushBack"  />
        <node index="86" lat="N60 17.309239" lon="E5 13.522503" isOnRunway="0" holdPointType="PushBack"  />
        <node index="87" lat="N60 17.333865" lon="E5 13.512741" isOnRunway="0" holdPointType="PushBack"  />
        <node index="88" lat="N60 17.357924" lon="E5 13.519841" isOnRunway="0" holdPointType="PushBack"  />
        <node index="89" lat="N60 17.381783" lon="E5 13.538857" isOnRunway="0" holdPointType="none"  />
        <node index="90" lat="N60 17.393836" lon="E5 13.584436" isOnRunway="0" holdPointType="none"  />
        <node index="91" lat="N60 17.399939" lon="E5 13.635647" isOnRunway="0" holdPointType="none"  />
        <node index="92" lat="N60 17.456308" lon="E5 13.686515" isOnRunway="0" holdPointType="PushBack"  />
        <node index="93" lat="N60 17.449715" lon="E5 13.636165" isOnRunway="0" holdPointType="none"  />
        <node index="94" lat="N60 17.448214" lon="E5 13.581482" isOnRunway="0" holdPointType="none"  />
        <node index="95" lat="N60 17.442663" lon="E5 13.526493" isOnRunway="0" holdPointType="none"  />
        <node index="96" lat="N60 17.441737" lon="E5 13.466549" isOnRunway="0" holdPointType="PushBack"  />
        <node index="97" lat="N60 17.397227" lon="E5 13.692802" isOnRunway="0" holdPointType="none"  />
        <node index="98" lat="N60 17.415012" lon="E5 13.713533" isOnRunway="0" holdPointType="PushBack"  />
        <node index="99" lat="N60 17.423744" lon="E5 13.677060" isOnRunway="0" holdPointType="none"  />
        <node index="100" lat="N60 17.429101" lon="E5 13.608955" isOnRunway="0" holdPointType="none"  />
        <node index="101" lat="N60 17.427002" lon="E5 13.636807" isOnRunway="0" holdPointType="PushBack"  />
        <node index="102" lat="N60 18.156036" lon="E5 13.792457" isOnRunway="0" holdPointType="PushBack"  />
        <node index="103" lat="N60 18.051868" lon="E5 13.636453" isOnRunway="0" holdPointType="PushBack"  />
        <node index="104" lat="N60 17.674883" lon="E5 13.502580" isOnRunway="0" holdPointType="PushBack"  />
        <node index="105" lat="N60 17.740603" lon="E5 13.453892" isOnRunway="0" holdPointType="none"  />
        <node index="106" lat="N60 17.719396" lon="E5 13.460958" isOnRunway="0" holdPointType="none"  />
        <node index="107" lat="N60 17.710373" lon="E5 13.485109" isOnRunway="0" holdPointType="none"  />
        <node index="108" lat="N60 17.711620" lon="E5 13.560718" isOnRunway="0" holdPointType="none"  />
        <node index="109" lat="N60 17.710465" lon="E5 13.500080" isOnRunway="0" holdPointType="none"  />
        <node index="110" lat="N60 17.701474" lon="E5 13.573734" isOnRunway="0" holdPointType="PushBack"  />
        <node index="111" lat="N60 17.675751" lon="E5 13.578871" isOnRunway="0" holdPointType="PushBack"  />
        <node index="112" lat="N60 17.666372" lon="E5 13.574005" isOnRunway="0" holdPointType="PushBack"  />
        <node index="113" lat="N60 18.065819" lon="E5 13.719128" isOnRunway="0" holdPointType="none"  />
        <node index="114" lat="N60 18.050693" lon="E5 13.729258" isOnRunway="0" holdPointType="PushBack"  />
        <node index="115" lat="N60 18.037081" lon="E5 13.727038" isOnRunway="0" holdPointType="PushBack"  />
        <node index="116" lat="N60 18.079094" lon="E5 13.660736" isOnRunway="0" holdPointType="PushBack"  />
        <node index="117" lat="N60 18.158202" lon="E5 13.758675" isOnRunway="0" holdPointType="none"  />
        <node index="118" lat="N60 18.143276" lon="E5 13.752781" isOnRunway="0" holdPointType="none"  />
        <node index="119" lat="N60 18.126220" lon="E5 13.740159" isOnRunway="0" holdPointType="none"  />
        <node index="120" lat="N60 18.105127" lon="E5 13.721693" isOnRunway="0" holdPointType="PushBack"  />
        <node index="121" lat="N60 18.070889" lon="E5 13.690733" isOnRunway="0" holdPointType="none"  />
        <node index="122" lat="N60 18.043278" lon="E5 13.666651" isOnRunway="0" holdPointType="PushBack"  />
        <node index="123" lat="N60 18.017967" lon="E5 13.648018" isOnRunway="0" holdPointType="PushBack"  />
        <node index="124" lat="N60 17.939125" lon="E5 13.601137" isOnRunway="0" holdPointType="none"  />
        <node index="125" lat="N60 17.913059" lon="E5 13.583899" isOnRunway="0" holdPointType="none"  />
        <node index="126" lat="N60 17.893538" lon="E5 13.558874" isOnRunway="0" holdPointType="none"  />
        <node index="127" lat="N60 17.876465" lon="E5 13.528097" isOnRunway="0" holdPointType="none"  />
        <node index="128" lat="N60 17.858549" lon="E5 13.476273" isOnRunway="0" holdPointType="none"  />
        <node index="129" lat="N60 17.853959" lon="E5 13.439813" isOnRunway="0" holdPointType="none"  />
        <node index="130" lat="N60 16.998866" lon="E5 13.557218" isOnRunway="0" holdPointType="none"  />
        <node index="131" lat="N60 17.840240" lon="E5 13.274552" isOnRunway="0" holdPointType="none"  />
        <node index="132" lat="N60 17.804222" lon="E5 13.286870" isOnRunway="0" holdPointType="none"  />
        <node index="133" lat="N60 17.789959" lon="E5 13.291575" isOnRunway="0" holdPointType="none"  />
        <node index="134" lat="N60 17.780842" lon="E5 13.294424" isOnRunway="0" holdPointType="none"  />
        <node index="135" lat="N60 17.755609" lon="E5 13.302852" isOnRunway="0" holdPointType="none"  />
        <node index="136" lat="N60 17.851913" lon="E5 13.416403" isOnRunway="0" holdPointType="none"  />
        <node index="137" lat="N60 17.810603" lon="E5 13.363643" isOnRunway="0" holdPointType="PushBack"  />
        <node index="138" lat="N60 17.795593" lon="E5 13.361032" isOnRunway="0" holdPointType="none"  />
        <node index="139" lat="N60 17.787117" lon="E5 13.371217" isOnRunway="0" holdPointType="PushBack"  />
        <node index="140" lat="N60 17.761884" lon="E5 13.379834" isOnRunway="0" holdPointType="PushBack"  />
        <node index="141" lat="N60 17.729183" lon="E5 13.312036" isOnRunway="0" holdPointType="none"  />
        <node index="142" lat="N60 17.643334" lon="E5 13.340844" isOnRunway="0" holdPointType="none"  />
        <node index="143" lat="N60 17.584514" lon="E5 13.360522" isOnRunway="0" holdPointType="none"  />
        <node index="144" lat="N60 17.564487" lon="E5 13.367192" isOnRunway="0" holdPointType="none"  />
        <node index="145" lat="N60 17.545092" lon="E5 13.373666" isOnRunway="0" holdPointType="none"  />
        <node index="146" lat="N60 17.525551" lon="E5 13.380238" isOnRunway="0" holdPointType="none"  />
        <node index="147" lat="N60 17.505815" lon="E5 13.386908" isOnRunway="0" holdPointType="none"  />
        <node index="148" lat="N60 17.486614" lon="E5 13.393382" isOnRunway="0" holdPointType="none"  />
        <node index="149" lat="N60 17.466490" lon="E5 13.400150" isOnRunway="0" holdPointType="none"  />
        <node index="150" lat="N60 17.413151" lon="E5 13.418096" isOnRunway="0" holdPointType="none"  />
        <node index="151" lat="N60 17.371210" lon="E5 13.432185" isOnRunway="0" holdPointType="none"  />
        <node index="152" lat="N60 17.416571" lon="E5 13.459508" isOnRunway="0" holdPointType="PushBack"  />
        <node index="153" lat="N60 17.420317" lon="E5 13.503860" isOnRunway="0" holdPointType="PushBack"  />
        <node index="154" lat="N60 17.424805" lon="E5 13.557080" isOnRunway="0" holdPointType="none"  />
        <node index="155" lat="N60 17.426227" lon="E5 13.573623" isOnRunway="0" holdPointType="PushBack"  />
        <node index="156" lat="N60 17.361099" lon="E5 13.435564" isOnRunway="0" holdPointType="none"  />
        <node index="157" lat="N60 17.329804" lon="E5 13.446065" isOnRunway="0" holdPointType="none"  />
        <node index="158" lat="N60 17.290780" lon="E5 13.459140" isOnRunway="0" holdPointType="none"  />
        <node index="159" lat="N60 17.235421" lon="E5 13.477733" isOnRunway="0" holdPointType="none"  />
        <node index="160" lat="N60 17.236292" lon="E5 13.487996" isOnRunway="0" holdPointType="none"  />
        <node index="161" lat="N60 17.245738" lon="E5 13.600291" isOnRunway="0" holdPointType="PushBack"  />
        <node index="162" lat="N60 17.252948" lon="E5 13.686599" isOnRunway="0" holdPointType="PushBack"  />
        <node index="163" lat="N60 17.212300" lon="E5 13.485524" isOnRunway="0" holdPointType="none"  />
        <node index="164" lat="N60 17.131755" lon="E5 13.512517" isOnRunway="0" holdPointType="none"  />
        <node index="165" lat="N60 17.109369" lon="E5 13.520087" isOnRunway="0" holdPointType="none"  />
        <node index="166" lat="N60 17.084524" lon="E5 13.528442" isOnRunway="0" holdPointType="none"  />
        <node index="167" lat="N60 17.060521" lon="E5 13.536535" isOnRunway="0" holdPointType="PushBack"  />
        <node index="168" lat="N60 17.043698" lon="E5 13.542278" isOnRunway="0" holdPointType="PushBack"  />
        <node index="169" lat="N60 17.017495" lon="E5 13.551023" isOnRunway="0" holdPointType="PushBack"  />
        <node index="170" lat="N60 16.836394" lon="E5 13.351612" isOnRunway="0" holdPointType="none"  />
        <node index="171" lat="N60 16.829116" lon="E5 13.366486" isOnRunway="0" holdPointType="none"  />
        <node index="172" lat="N60 16.825478" lon="E5 13.385734" isOnRunway="0" holdPointType="none"  />
        <node index="173" lat="N60 16.825633" lon="E5 13.406046" isOnRunway="0" holdPointType="none"  />
        <node index="174" lat="N60 16.829592" lon="E5 13.454525" isOnRunway="0" holdPointType="none"  />
        <node index="175" lat="N60 16.832434" lon="E5 13.487497" isOnRunway="0" holdPointType="none"  />
        <node index="176" lat="N60 16.833931" lon="E5 13.497725" isOnRunway="0" holdPointType="none"  />
        <node index="177" lat="N60 16.838683" lon="E5 13.512416" isOnRunway="0" holdPointType="none"  />
        <node index="178" lat="N60 16.845346" lon="E5 13.523149" isOnRunway="0" holdPointType="none"  />
        <node index="179" lat="N60 16.852526" lon="E5 13.528567" isOnRunway="0" holdPointType="none"  />
        <node index="180" lat="N60 16.863534" lon="E5 13.529111" isOnRunway="0" holdPointType="none"  />
        <node index="181" lat="N60 18.371759" lon="E5 13.022501" isOnRunway="0" holdPointType="none"  />
        <node index="182" lat="N60 18.383660" lon="E5 13.016633" isOnRunway="0" holdPointType="none"  />
        <node index="183" lat="N60 18.392644" lon="E5 13.002623" isOnRunway="0" holdPointType="none"  />
        <node index="184" lat="N60 18.397870" lon="E5 12.982867" isOnRunway="0" holdPointType="none"  />
        <node index="185" lat="N60 18.398072" lon="E5 12.960904" isOnRunway="0" holdPointType="none"  />
        <node index="186" lat="N60 18.261287" lon="E5 12.961040" isOnRunway="0" holdPointType="none"  />
        <node index="187" lat="N60 18.265934" lon="E5 13.016690" isOnRunway="0" holdPointType="none"  />
        <node index="188" lat="N60 18.264190" lon="E5 13.041313" isOnRunway="0" holdPointType="none"  />
        <node index="189" lat="N60 18.259815" lon="E5 13.053463" isOnRunway="0" holdPointType="none"  />
        <node index="190" lat="N60 18.251179" lon="E5 13.063003" isOnRunway="0" holdPointType="none"  />
        <node index="191" lat="N60 18.249730" lon="E5 12.908773" isOnRunway="0" holdPointType="none"  />
        <node index="192" lat="N60 18.243803" lon="E5 12.893055" isOnRunway="0" holdPointType="none"  />
        <node index="193" lat="N60 18.234443" lon="E5 12.882520" isOnRunway="0" holdPointType="none"  />
        <node index="194" lat="N60 18.363298" lon="E5 12.832184" isOnRunway="1" holdPointType="none"  />
        <node index="195" lat="N60 18.369197" lon="E5 12.833125" isOnRunway="0" holdPointType="none"  />
        <node index="196" lat="N60 18.377936" lon="E5 12.839670" isOnRunway="0" holdPointType="none"  />
        <node index="197" lat="N60 18.384338" lon="E5 12.849571" isOnRunway="0" holdPointType="none"  />
        <node index="198" lat="N60 18.388239" lon="E5 12.860137" isOnRunway="0" holdPointType="none"  />
        <node index="199" lat="N60 18.391054" lon="E5 12.876383" isOnRunway="0" holdPointType="none"  />
        <node index="200" lat="N60 18.395455" lon="E5 12.929167" isOnRunway="0" holdPointType="none"  />
        <node index="201" lat="N60 16.988190" lon="E5 13.555344" isOnRunway="0" holdPointType="none"  />
        <node index="202" lat="N60 16.991870" lon="E5 13.555970" isOnRunway="0" holdPointType="none"  />
        <node index="203" lat="N60 16.994090" lon="E5 13.556377" isOnRunway="0" holdPointType="none"  />
        <node index="204" lat="N60 16.979217" lon="E5 13.533617" isOnRunway="0" holdPointType="none"  />
        <node index="205" lat="N60 16.963832" lon="E5 13.386418" isOnRunway="0" holdPointType="none"  />
        <node index="206" lat="N60 18.397484" lon="E5 12.820699" isOnRunway="1" holdPointType="none"  />
        <node index="207" lat="N60 18.008185" lon="E5 13.144625" isOnRunway="0" holdPointType="none"  />
        <node index="208" lat="N60 17.834357" lon="E5 13.203013" isOnRunway="0" holdPointType="none"  />
        <node index="209" lat="N60 17.637431" lon="E5 13.269160" isOnRunway="0" holdPointType="none"  />
        <node index="210" lat="N60 17.355320" lon="E5 13.363909" isOnRunway="0" holdPointType="none"  />
        <node index="211" lat="N60 17.206535" lon="E5 13.413897" isOnRunway="0" holdPointType="none"  />
        <node index="212" lat="N60 16.972378" lon="E5 13.492548" isOnRunway="0" holdPointType="none"  />
        <node index="213" lat="N60 18.015593" lon="E5 13.137836" isOnRunway="0" holdPointType="none"  />
        <node index="214" lat="N60 18.021920" lon="E5 13.125890" isOnRunway="0" holdPointType="none"  />
        <node index="215" lat="N60 18.026207" lon="E5 13.110353" isOnRunway="0" holdPointType="none"  />
        <node index="216" lat="N60 18.027584" lon="E5 13.086385" isOnRunway="0" holdPointType="none"  />
        <node index="217" lat="N60 16.809265" lon="E5 13.354250" isOnRunway="1" holdPointType="none"  />
        <node index="218" lat="N60 16.845502" lon="E5 13.342076" isOnRunway="1" holdPointType="none"  />
        <node index="219" lat="N60 16.973920" lon="E5 13.298936" isOnRunway="1" holdPointType="none"  />
        <node index="220" lat="N60 17.190868" lon="E5 13.226053" isOnRunway="1" holdPointType="none"  />
        <node index="221" lat="N60 17.339796" lon="E5 13.176022" isOnRunway="1" holdPointType="none"  />
        <node index="222" lat="N60 17.621842" lon="E5 13.081271" isOnRunway="1" holdPointType="none"  />
        <node index="223" lat="N60 17.818801" lon="E5 13.015103" isOnRunway="1" holdPointType="none"  />
        <node index="224" lat="N60 18.016189" lon="E5 12.948793" isOnRunway="1" holdPointType="none"  />
        <node index="225" lat="N60 18.222578" lon="E5 12.879457" isOnRunway="1" holdPointType="none"  />
        <node index="226" lat="N60 17.425464" lon="E5 13.707625" isOnRunway="0" holdPointType="none"  />
        <node index="227" lat="N60 17.432239" lon="E5 13.636137" isOnRunway="0" holdPointType="none"  />
        <node index="228" lat="N60 17.424755" lon="E5 13.571260" isOnRunway="0" holdPointType="none"  />
        <node index="229" lat="N60 17.402845" lon="E5 13.518258" isOnRunway="0" holdPointType="none"  />
        <node index="230" lat="N60 17.367003" lon="E5 13.495427" isOnRunway="0" holdPointType="none"  />
        <node index="231" lat="N60 17.329899" lon="E5 13.486559" isOnRunway="0" holdPointType="none"  />
        <node index="232" lat="N60 17.294845" lon="E5 13.503653" isOnRunway="0" holdPointType="none"  />
        <node index="233" lat="N60 17.263294" lon="E5 13.545752" isOnRunway="0" holdPointType="none"  />
        <node index="234" lat="N60 17.250839" lon="E5 13.607620" isOnRunway="0" holdPointType="none"  />
        <node index="235" lat="N60 17.256576" lon="E5 13.673621" isOnRunway="0" holdPointType="none"  />
        <node index="236" lat="N60 17.271549" lon="E5 13.737724" isOnRunway="0" holdPointType="none"  />
        <node index="237" lat="N60 17.563076" lon="E5 13.428908" isOnRunway="0" holdPointType="none"  />
        <node index="238" lat="N60 17.543409" lon="E5 13.435579" isOnRunway="0" holdPointType="none"  />
        <node index="239" lat="N60 17.523812" lon="E5 13.442145" isOnRunway="0" holdPointType="none"  />
        <node index="240" lat="N60 17.504183" lon="E5 13.448850" isOnRunway="0" holdPointType="none"  />
        <node index="241" lat="N60 17.484533" lon="E5 13.455380" isOnRunway="0" holdPointType="none"  />
        <node index="242" lat="N60 17.464952" lon="E5 13.461909" isOnRunway="0" holdPointType="none"  />
        <node index="243" lat="N60 17.445236" lon="E5 13.468519" isOnRunway="0" holdPointType="none"  />
        <node index="244" lat="N60 17.425923" lon="E5 13.450133" isOnRunway="0" holdPointType="none"  />
        <node index="245" lat="N60 17.413214" lon="E5 13.512647" isOnRunway="0" holdPointType="none"  />
        <node index="246" lat="N60 17.415227" lon="E5 13.575544" isOnRunway="0" holdPointType="none"  />
        <node index="247" lat="N60 17.416419" lon="E5 13.637218" isOnRunway="0" holdPointType="none"  />
        <node index="248" lat="N60 17.456442" lon="E5 13.659161" isOnRunway="0" holdPointType="none"  />
        <node index="249" lat="N60 17.133638" lon="E5 13.566221" isOnRunway="0" holdPointType="none"  />
        <node index="250" lat="N60 17.110422" lon="E5 13.566466" isOnRunway="0" holdPointType="none"  />
        <node index="251" lat="N60 17.085487" lon="E5 13.574498" isOnRunway="0" holdPointType="none"  />
        <node index="252" lat="N60 17.059496" lon="E5 13.559647" isOnRunway="0" holdPointType="none"  />
        <node index="253" lat="N60 17.044907" lon="E5 13.558341" isOnRunway="0" holdPointType="none"  />
        <node index="254" lat="N60 17.017172" lon="E5 13.567911" isOnRunway="0" holdPointType="none"  />
        <node index="255" lat="N60 16.988794" lon="E5 13.572812" isOnRunway="0" holdPointType="none"  />
        <node index="256" lat="N60 16.989530" lon="E5 13.588974" isOnRunway="0" holdPointType="none"  />
        <node index="257" lat="N60 16.960654" lon="E5 13.580723" isOnRunway="0" holdPointType="none"  />
        <node index="258" lat="N60 16.983733" lon="E5 13.614976" isOnRunway="0" holdPointType="none"  />
        <node index="259" lat="N60 17.635671" lon="E5 13.503476" isOnRunway="0" holdPointType="none"  />
        <node index="260" lat="N60 18.160403" lon="E5 13.841948" isOnRunway="0" holdPointType="none"  />
        <node index="261" lat="N60 18.170614" lon="E5 13.828907" isOnRunway="0" holdPointType="none"  />
        <node index="262" lat="N60 18.108938" lon="E5 13.679717" isOnRunway="0" holdPointType="none"  />
        <node index="263" lat="N60 18.045770" lon="E5 13.647857" isOnRunway="0" holdPointType="none"  />
        <node index="264" lat="N60 18.069782" lon="E5 13.611584" isOnRunway="0" holdPointType="none"  />
        <node index="265" lat="N60 18.113063" lon="E5 13.635642" isOnRunway="0" holdPointType="none"  />
        <node index="266" lat="N60 18.050414" lon="E5 13.780216" isOnRunway="0" holdPointType="none"  />
        <node index="267" lat="N60 18.042196" lon="E5 13.781465" isOnRunway="0" holdPointType="none"  />
        <node index="268" lat="N60 18.026870" lon="E5 13.779819" isOnRunway="0" holdPointType="none"  />
        <node index="269" lat="N60 18.039662" lon="E5 13.669041" isOnRunway="0" holdPointType="none"  />
        <node index="270" lat="N60 18.085947" lon="E5 13.633375" isOnRunway="0" holdPointType="none"  />
        <node index="271" lat="N60 18.076200" lon="E5 13.590032" isOnRunway="0" holdPointType="none"  />
        <node index="272" lat="N60 18.018789" lon="E5 13.629253" isOnRunway="0" holdPointType="none"  />
        <node index="273" lat="N60 18.035722" lon="E5 13.583986" isOnRunway="0" holdPointType="none"  />
        <node index="274" lat="N60 17.731452" lon="E5 13.616796" isOnRunway="0" holdPointType="none"  />
        <node index="275" lat="N60 17.722447" lon="E5 13.616561" isOnRunway="0" holdPointType="none"  />
        <node index="276" lat="N60 17.712674" lon="E5 13.617359" isOnRunway="0" holdPointType="none"  />
        <node index="277" lat="N60 17.703134" lon="E5 13.615058" isOnRunway="0" holdPointType="none"  />
        <node index="278" lat="N60 17.693360" lon="E5 13.615951" isOnRunway="0" holdPointType="none"  />
        <node index="279" lat="N60 17.676293" lon="E5 13.620443" isOnRunway="0" holdPointType="none"  />
        <node index="280" lat="N60 17.668553" lon="E5 13.625075" isOnRunway="0" holdPointType="none"  />
        <node index="281" lat="N60 17.628765" lon="E5 13.597228" isOnRunway="0" holdPointType="none"  />
        <node index="282" lat="N60 17.628132" lon="E5 13.575610" isOnRunway="0" holdPointType="none"  />
        <node index="283" lat="N60 17.675889" lon="E5 13.580873" isOnRunway="0" holdPointType="none"  />
        <node index="284" lat="N60 17.816413" lon="E5 13.399054" isOnRunway="0" holdPointType="none"  />
        <node index="285" lat="N60 17.801375" lon="E5 13.396237" isOnRunway="0" holdPointType="none"  />
        <node index="286" lat="N60 17.792993" lon="E5 13.406591" isOnRunway="0" holdPointType="none"  />
        <node index="287" lat="N60 17.767793" lon="E5 13.414767" isOnRunway="0" holdPointType="none"  />
 </TaxiNodes>
 <TaxiWaySegments>
        <arc begin="195" end="194" isPushBackRoute="0" name="A1"  />
        <arc begin="194" end="195" isPushBackRoute="0" name="A1"  />
        <arc begin="196" end="195" isPushBackRoute="0" name="A1"  />
        <arc begin="195" end="196" isPushBackRoute="0" name="A1"  />
        <arc begin="197" end="196" isPushBackRoute="0" name="A1"  />
        <arc begin="196" end="197" isPushBackRoute="0" name="A1"  />
        <arc begin="198" end="197" isPushBackRoute="0" name="A1"  />
        <arc begin="197" end="198" isPushBackRoute="0" name="A1"  />
        <arc begin="199" end="198" isPushBackRoute="0" name="A1"  />
        <arc begin="198" end="199" isPushBackRoute="0" name="A1"  />
        <arc begin="200" end="199" isPushBackRoute="0" name="A1"  />
        <arc begin="199" end="200" isPushBackRoute="0" name="A1"  />
        <arc begin="186" end="187" isPushBackRoute="0" name="A2"  />
        <arc begin="187" end="188" isPushBackRoute="0" name="A2"  />
        <arc begin="188" end="189" isPushBackRoute="0" name="A2"  />
        <arc begin="189" end="190" isPushBackRoute="0" name="A2"  />
        <arc begin="191" end="186" isPushBackRoute="0" name="A2"  />
        <arc begin="192" end="191" isPushBackRoute="0" name="A2"  />
        <arc begin="193" end="192" isPushBackRoute="0" name="A2"  />
        <arc begin="225" end="193" isPushBackRoute="0" name="A2"  />
        <arc begin="213" end="207" isPushBackRoute="0" name="A3"  />
        <arc begin="214" end="213" isPushBackRoute="0" name="A3"  />
        <arc begin="215" end="214" isPushBackRoute="0" name="A3"  />
        <arc begin="216" end="215" isPushBackRoute="0" name="A3"  />
        <arc begin="224" end="216" isPushBackRoute="0" name="A3"  />
        <arc begin="223" end="208" isPushBackRoute="0" name="A4"  />
        <arc begin="222" end="209" isPushBackRoute="0" name="A5"  />
        <arc begin="221" end="210" isPushBackRoute="0" name="A6"  />
        <arc begin="220" end="211" isPushBackRoute="0" name="A7"  />
        <arc begin="205" end="212" isPushBackRoute="0" name="A8"  />
        <arc begin="219" end="205" isPushBackRoute="0" name="A8"  />
        <arc begin="170" end="218" isPushBackRoute="0" name="A9"  />
        <arc begin="218" end="170" isPushBackRoute="0" name="A9"  />
        <arc begin="171" end="170" isPushBackRoute="0" name="A9"  />
        <arc begin="170" end="171" isPushBackRoute="0" name="A9"  />
        <arc begin="172" end="171" isPushBackRoute="0" name="A9"  />
        <arc begin="171" end="172" isPushBackRoute="0" name="A9"  />
        <arc begin="173" end="172" isPushBackRoute="0" name="A9"  />
        <arc begin="172" end="173" isPushBackRoute="0" name="A9"  />
        <arc begin="174" end="173" isPushBackRoute="0" name="A9"  />
        <arc begin="173" end="174" isPushBackRoute="0" name="A9"  />
        <arc begin="175" end="174" isPushBackRoute="0" name="Y"  />
        <arc begin="174" end="175" isPushBackRoute="0" name="Y"  />
        <arc begin="177" end="176" isPushBackRoute="0" name="Y"  />
        <arc begin="176" end="177" isPushBackRoute="0" name="Y"  />
        <arc begin="178" end="177" isPushBackRoute="0" name="Y"  />
        <arc begin="177" end="178" isPushBackRoute="0" name="Y"  />
        <arc begin="179" end="178" isPushBackRoute="0" name="Y"  />
        <arc begin="178" end="179" isPushBackRoute="0" name="Y"  />
        <arc begin="180" end="179" isPushBackRoute="0" name="Y"  />
        <arc begin="179" end="180" isPushBackRoute="0" name="Y"  />
        <arc begin="181" end="190" isPushBackRoute="0" name="Y"  />
        <arc begin="190" end="181" isPushBackRoute="0" name="Y"  />
        <arc begin="190" end="207" isPushBackRoute="0" name="Y"  />
        <arc begin="207" end="190" isPushBackRoute="0" name="Y"  />
        <arc begin="207" end="208" isPushBackRoute="0" name="Y"  />
        <arc begin="208" end="207" isPushBackRoute="0" name="Y"  />
        <arc begin="208" end="209" isPushBackRoute="0" name="Y"  />
        <arc begin="209" end="208" isPushBackRoute="0" name="Y"  />
        <arc begin="209" end="210" isPushBackRoute="0" name="Y"  />
        <arc begin="210" end="209" isPushBackRoute="0" name="Y"  />
        <arc begin="210" end="211" isPushBackRoute="0" name="Y"  />
        <arc begin="211" end="210" isPushBackRoute="0" name="Y"  />
        <arc begin="211" end="212" isPushBackRoute="0" name="Y"  />
        <arc begin="212" end="211" isPushBackRoute="0" name="Y"  />
        <arc begin="212" end="180" isPushBackRoute="0" name="Y"  />
        <arc begin="180" end="212" isPushBackRoute="0" name="Y"  />
        <arc begin="182" end="181" isPushBackRoute="0" name="Y"  />
        <arc begin="181" end="182" isPushBackRoute="0" name="Y"  />
        <arc begin="183" end="182" isPushBackRoute="0" name="Y"  />
        <arc begin="182" end="183" isPushBackRoute="0" name="Y"  />
        <arc begin="184" end="183" isPushBackRoute="0" name="Y"  />
        <arc begin="183" end="184" isPushBackRoute="0" name="Y"  />
        <arc begin="185" end="184" isPushBackRoute="0" name="Y"  />
        <arc begin="184" end="185" isPushBackRoute="0" name="Y"  />
        <arc begin="200" end="185" isPushBackRoute="0" name="Y"  />
        <arc begin="185" end="200" isPushBackRoute="0" name="Y"  />
        <arc begin="176" end="175" isPushBackRoute="0" name="Y"  />
        <arc begin="175" end="176" isPushBackRoute="0" name="Y"  />
        <arc begin="131" end="132" isPushBackRoute="0" name="W"  />
        <arc begin="132" end="131" isPushBackRoute="0" name="W"  />
        <arc begin="132" end="133" isPushBackRoute="0" name="W"  />
        <arc begin="133" end="132" isPushBackRoute="0" name="W"  />
        <arc begin="133" end="134" isPushBackRoute="0" name="W"  />
        <arc begin="134" end="133" isPushBackRoute="0" name="W"  />
        <arc begin="134" end="135" isPushBackRoute="0" name="W"  />
        <arc begin="135" end="134" isPushBackRoute="0" name="W"  />
        <arc begin="135" end="141" isPushBackRoute="0" name="W"  />
        <arc begin="141" end="135" isPushBackRoute="0" name="W"  />
        <arc begin="141" end="142" isPushBackRoute="0" name="W"  />
        <arc begin="142" end="141" isPushBackRoute="0" name="W"  />
        <arc begin="142" end="143" isPushBackRoute="0" name="W"  />
        <arc begin="143" end="142" isPushBackRoute="0" name="W"  />
        <arc begin="143" end="144" isPushBackRoute="0" name="W"  />
        <arc begin="144" end="143" isPushBackRoute="0" name="W"  />
        <arc begin="144" end="145" isPushBackRoute="0" name="W"  />
        <arc begin="145" end="144" isPushBackRoute="0" name="W"  />
        <arc begin="145" end="146" isPushBackRoute="0" name="W"  />
        <arc begin="146" end="145" isPushBackRoute="0" name="W"  />
        <arc begin="146" end="147" isPushBackRoute="0" name="W"  />
        <arc begin="147" end="146" isPushBackRoute="0" name="W"  />
        <arc begin="147" end="148" isPushBackRoute="0" name="W"  />
        <arc begin="148" end="147" isPushBackRoute="0" name="W"  />
        <arc begin="148" end="149" isPushBackRoute="0" name="W"  />
        <arc begin="149" end="148" isPushBackRoute="0" name="W"  />
        <arc begin="149" end="150" isPushBackRoute="0" name="W"  />
        <arc begin="150" end="149" isPushBackRoute="0" name="W"  />
        <arc begin="150" end="151" isPushBackRoute="0" name="W"  />
        <arc begin="151" end="150" isPushBackRoute="0" name="W"  />
        <arc begin="151" end="156" isPushBackRoute="0" name="W"  />
        <arc begin="156" end="151" isPushBackRoute="0" name="W"  />
        <arc begin="156" end="157" isPushBackRoute="0" name="W"  />
        <arc begin="157" end="156" isPushBackRoute="0" name="W"  />
        <arc begin="157" end="158" isPushBackRoute="0" name="W"  />
        <arc begin="158" end="157" isPushBackRoute="0" name="W"  />
        <arc begin="158" end="159" isPushBackRoute="0" name="W"  />
        <arc begin="159" end="158" isPushBackRoute="0" name="W"  />
        <arc begin="159" end="163" isPushBackRoute="0" name="W"  />
        <arc begin="163" end="159" isPushBackRoute="0" name="W"  />
        <arc begin="163" end="164" isPushBackRoute="0" name="W"  />
        <arc begin="164" end="163" isPushBackRoute="0" name="W"  />
        <arc begin="164" end="165" isPushBackRoute="0" name="W"  />
        <arc begin="165" end="164" isPushBackRoute="0" name="W"  />
        <arc begin="165" end="166" isPushBackRoute="0" name="W"  />
        <arc begin="166" end="165" isPushBackRoute="0" name="W"  />
        <arc begin="166" end="167" isPushBackRoute="0" name="W"  />
        <arc begin="167" end="166" isPushBackRoute="0" name="W"  />
        <arc begin="167" end="168" isPushBackRoute="0" name="W"  />
        <arc begin="168" end="167" isPushBackRoute="0" name="W"  />
        <arc begin="168" end="169" isPushBackRoute="0" name="W"  />
        <arc begin="169" end="168" isPushBackRoute="0" name="W"  />
        <arc begin="169" end="130" isPushBackRoute="0" name="W"  />
        <arc begin="130" end="169" isPushBackRoute="0" name="W"  />
        <arc begin="136" end="105" isPushBackRoute="0" name="U"  />
        <arc begin="105" end="136" isPushBackRoute="0" name="U"  />
        <arc begin="105" end="106" isPushBackRoute="0" name="U"  />
        <arc begin="106" end="105" isPushBackRoute="0" name="U"  />
        <arc begin="118" end="117" isPushBackRoute="0" name="B"  />
        <arc begin="117" end="118" isPushBackRoute="0" name="B"  />
        <arc begin="119" end="118" isPushBackRoute="0" name="B"  />
        <arc begin="118" end="119" isPushBackRoute="0" name="B"  />
        <arc begin="120" end="119" isPushBackRoute="0" name="B"  />
        <arc begin="119" end="120" isPushBackRoute="0" name="B"  />
        <arc begin="121" end="120" isPushBackRoute="0" name="B"  />
        <arc begin="120" end="121" isPushBackRoute="0" name="B"  />
        <arc begin="122" end="121" isPushBackRoute="0" name="B"  />
        <arc begin="121" end="122" isPushBackRoute="0" name="B"  />
        <arc begin="123" end="122" isPushBackRoute="0" name="B"  />
        <arc begin="122" end="123" isPushBackRoute="0" name="B"  />
        <arc begin="124" end="123" isPushBackRoute="0" name="B"  />
        <arc begin="123" end="124" isPushBackRoute="0" name="B"  />
        <arc begin="125" end="124" isPushBackRoute="0" name="B"  />
        <arc begin="124" end="125" isPushBackRoute="0" name="B"  />
        <arc begin="126" end="125" isPushBackRoute="0" name="B"  />
        <arc begin="125" end="126" isPushBackRoute="0" name="B"  />
        <arc begin="127" end="126" isPushBackRoute="0" name="B"  />
        <arc begin="126" end="127" isPushBackRoute="0" name="B"  />
        <arc begin="128" end="127" isPushBackRoute="0" name="B"  />
        <arc begin="127" end="128" isPushBackRoute="0" name="B"  />
        <arc begin="129" end="128" isPushBackRoute="0" name="B"  />
        <arc begin="128" end="129" isPushBackRoute="0" name="B"  />
        <arc begin="131" end="136" isPushBackRoute="0" name="B"  />
        <arc begin="136" end="131" isPushBackRoute="0" name="B"  />
        <arc begin="136" end="129" isPushBackRoute="0" name="B"  />
        <arc begin="129" end="136" isPushBackRoute="0" name="B"  />
        <arc begin="208" end="131" isPushBackRoute="0" name="B"  />
        <arc begin="131" end="208" isPushBackRoute="0" name="B"  />
        <arc begin="209" end="142" isPushBackRoute="0" name="C"  />
        <arc begin="142" end="209" isPushBackRoute="0" name="C"  />
        <arc begin="210" end="156" isPushBackRoute="0" name="E"  />
        <arc begin="156" end="210" isPushBackRoute="0" name="E"  />
        <arc begin="211" end="163" isPushBackRoute="0" name="G"  />
        <arc begin="163" end="211" isPushBackRoute="0" name="G"  />
        <arc begin="201" end="202" isPushBackRoute="0" name="H"  />
        <arc begin="202" end="201" isPushBackRoute="0" name="H"  />
        <arc begin="202" end="203" isPushBackRoute="0" name="H"  />
        <arc begin="203" end="202" isPushBackRoute="0" name="H"  />
        <arc begin="203" end="130" isPushBackRoute="0" name="H"  />
        <arc begin="130" end="203" isPushBackRoute="0" name="H"  />
        <arc begin="204" end="201" isPushBackRoute="0" name="H"  />
        <arc begin="201" end="204" isPushBackRoute="0" name="H"  />
        <arc begin="212" end="204" isPushBackRoute="0" name="H"  />
        <arc begin="204" end="212" isPushBackRoute="0" name="H"  />
        <arc begin="105" end="141" isPushBackRoute="0" name="J"  />
        <arc begin="141" end="105" isPushBackRoute="0" name="J"  />
        <arc begin="149" end="62" isPushBackRoute="0" name=""  />
        <arc begin="62" end="149" isPushBackRoute="0" name=""  />
        <arc begin="148" end="63" isPushBackRoute="0" name=""  />
        <arc begin="63" end="148" isPushBackRoute="0" name=""  />
        <arc begin="147" end="64" isPushBackRoute="0" name=""  />
        <arc begin="64" end="147" isPushBackRoute="0" name=""  />
        <arc begin="146" end="65" isPushBackRoute="0" name=""  />
        <arc begin="65" end="146" isPushBackRoute="0" name=""  />
        <arc begin="145" end="66" isPushBackRoute="0" name=""  />
        <arc begin="66" end="145" isPushBackRoute="0" name=""  />
        <arc begin="144" end="67" isPushBackRoute="0" name=""  />
        <arc begin="67" end="144" isPushBackRoute="0" name=""  />
        <arc begin="143" end="68" isPushBackRoute="0" name=""  />
        <arc begin="68" end="143" isPushBackRoute="0" name=""  />
        <arc begin="70" end="69" isPushBackRoute="0" name=""  />
        <arc begin="69" end="70" isPushBackRoute="0" name=""  />
        <arc begin="71" end="70" isPushBackRoute="0" name=""  />
        <arc begin="70" end="71" isPushBackRoute="0" name=""  />
        <arc begin="201" end="71" isPushBackRoute="0" name=""  />
        <arc begin="71" end="201" isPushBackRoute="0" name=""  />
        <arc begin="202" end="72" isPushBackRoute="0" name=""  />
        <arc begin="72" end="202" isPushBackRoute="0" name=""  />
        <arc begin="203" end="73" isPushBackRoute="0" name=""  />
        <arc begin="73" end="203" isPushBackRoute="0" name=""  />
        <arc begin="169" end="74" isPushBackRoute="0" name=""  />
        <arc begin="74" end="169" isPushBackRoute="0" name=""  />
        <arc begin="168" end="75" isPushBackRoute="0" name=""  />
        <arc begin="75" end="168" isPushBackRoute="0" name=""  />
        <arc begin="167" end="76" isPushBackRoute="0" name=""  />
        <arc begin="76" end="167" isPushBackRoute="0" name=""  />
        <arc begin="166" end="77" isPushBackRoute="0" name=""  />
        <arc begin="77" end="166" isPushBackRoute="0" name=""  />
        <arc begin="165" end="78" isPushBackRoute="0" name=""  />
        <arc begin="78" end="165" isPushBackRoute="0" name=""  />
        <arc begin="164" end="79" isPushBackRoute="0" name=""  />
        <arc begin="79" end="164" isPushBackRoute="0" name=""  />
        <arc begin="162" end="80" isPushBackRoute="0" name=""  />
        <arc begin="80" end="162" isPushBackRoute="0" name=""  />
        <arc begin="161" end="81" isPushBackRoute="0" name=""  />
        <arc begin="81" end="161" isPushBackRoute="0" name=""  />
        <arc begin="160" end="82" isPushBackRoute="0" name=""  />
        <arc begin="82" end="160" isPushBackRoute="0" name=""  />
        <arc begin="98" end="97" isPushBackRoute="0" name=""  />
        <arc begin="97" end="98" isPushBackRoute="0" name=""  />
        <arc begin="84" end="83" isPushBackRoute="0" name=""  />
        <arc begin="83" end="84" isPushBackRoute="0" name=""  />
        <arc begin="85" end="84" isPushBackRoute="0" name=""  />
        <arc begin="84" end="85" isPushBackRoute="0" name=""  />
        <arc begin="159" end="160" isPushBackRoute="0" name=""  />
        <arc begin="160" end="159" isPushBackRoute="0" name=""  />
        <arc begin="160" end="161" isPushBackRoute="0" name=""  />
        <arc begin="161" end="160" isPushBackRoute="0" name=""  />
        <arc begin="161" end="162" isPushBackRoute="0" name=""  />
        <arc begin="162" end="161" isPushBackRoute="0" name=""  />
        <arc begin="162" end="85" isPushBackRoute="0" name=""  />
        <arc begin="85" end="162" isPushBackRoute="0" name=""  />
        <arc begin="158" end="86" isPushBackRoute="0" name=""  />
        <arc begin="86" end="158" isPushBackRoute="0" name=""  />
        <arc begin="157" end="87" isPushBackRoute="0" name=""  />
        <arc begin="87" end="157" isPushBackRoute="0" name=""  />
        <arc begin="151" end="88" isPushBackRoute="0" name=""  />
        <arc begin="88" end="151" isPushBackRoute="0" name=""  />
        <arc begin="152" end="89" isPushBackRoute="0" name=""  />
        <arc begin="89" end="152" isPushBackRoute="0" name=""  />
        <arc begin="154" end="90" isPushBackRoute="0" name=""  />
        <arc begin="90" end="154" isPushBackRoute="0" name=""  />
        <arc begin="101" end="91" isPushBackRoute="0" name=""  />
        <arc begin="91" end="101" isPushBackRoute="0" name=""  />
        <arc begin="99" end="92" isPushBackRoute="0" name=""  />
        <arc begin="92" end="99" isPushBackRoute="0" name=""  />
        <arc begin="99" end="98" isPushBackRoute="0" name=""  />
        <arc begin="98" end="99" isPushBackRoute="0" name=""  />
        <arc begin="100" end="101" isPushBackRoute="0" name=""  />
        <arc begin="101" end="100" isPushBackRoute="0" name=""  />
        <arc begin="101" end="93" isPushBackRoute="0" name=""  />
        <arc begin="93" end="101" isPushBackRoute="0" name=""  />
        <arc begin="101" end="99" isPushBackRoute="0" name=""  />
        <arc begin="99" end="101" isPushBackRoute="0" name=""  />
        <arc begin="155" end="94" isPushBackRoute="0" name=""  />
        <arc begin="94" end="155" isPushBackRoute="0" name=""  />
        <arc begin="153" end="95" isPushBackRoute="0" name=""  />
        <arc begin="95" end="153" isPushBackRoute="0" name=""  />
        <arc begin="152" end="96" isPushBackRoute="0" name=""  />
        <arc begin="96" end="152" isPushBackRoute="0" name=""  />
        <arc begin="150" end="152" isPushBackRoute="0" name=""  />
        <arc begin="152" end="150" isPushBackRoute="0" name=""  />
        <arc begin="152" end="153" isPushBackRoute="0" name=""  />
        <arc begin="153" end="152" isPushBackRoute="0" name=""  />
        <arc begin="153" end="154" isPushBackRoute="0" name=""  />
        <arc begin="154" end="153" isPushBackRoute="0" name=""  />
        <arc begin="154" end="155" isPushBackRoute="0" name=""  />
        <arc begin="155" end="154" isPushBackRoute="0" name=""  />
        <arc begin="155" end="100" isPushBackRoute="0" name=""  />
        <arc begin="100" end="155" isPushBackRoute="0" name=""  />
        <arc begin="102" end="117" isPushBackRoute="0" name=""  />
        <arc begin="117" end="102" isPushBackRoute="0" name=""  />
        <arc begin="103" end="122" isPushBackRoute="0" name=""  />
        <arc begin="122" end="103" isPushBackRoute="0" name=""  />
        <arc begin="140" end="135" isPushBackRoute="0" name=""  />
        <arc begin="135" end="140" isPushBackRoute="0" name=""  />
        <arc begin="139" end="134" isPushBackRoute="0" name=""  />
        <arc begin="134" end="139" isPushBackRoute="0" name=""  />
        <arc begin="104" end="109" isPushBackRoute="0" name=""  />
        <arc begin="109" end="104" isPushBackRoute="0" name=""  />
        <arc begin="138" end="133" isPushBackRoute="0" name=""  />
        <arc begin="133" end="138" isPushBackRoute="0" name=""  />
        <arc begin="107" end="106" isPushBackRoute="0" name=""  />
        <arc begin="106" end="107" isPushBackRoute="0" name=""  />
        <arc begin="108" end="109" isPushBackRoute="0" name=""  />
        <arc begin="109" end="108" isPushBackRoute="0" name=""  />
        <arc begin="109" end="107" isPushBackRoute="0" name=""  />
        <arc begin="107" end="109" isPushBackRoute="0" name=""  />
        <arc begin="110" end="108" isPushBackRoute="0" name=""  />
        <arc begin="108" end="110" isPushBackRoute="0" name=""  />
        <arc begin="111" end="110" isPushBackRoute="0" name=""  />
        <arc begin="110" end="111" isPushBackRoute="0" name=""  />
        <arc begin="112" end="111" isPushBackRoute="0" name=""  />
        <arc begin="111" end="112" isPushBackRoute="0" name=""  />
        <arc begin="113" end="121" isPushBackRoute="0" name=""  />
        <arc begin="121" end="113" isPushBackRoute="0" name=""  />
        <arc begin="114" end="113" isPushBackRoute="0" name=""  />
        <arc begin="113" end="114" isPushBackRoute="0" name=""  />
        <arc begin="115" end="114" isPushBackRoute="0" name=""  />
        <arc begin="114" end="115" isPushBackRoute="0" name=""  />
        <arc begin="116" end="121" isPushBackRoute="0" name=""  />
        <arc begin="121" end="116" isPushBackRoute="0" name=""  />
        <arc begin="137" end="132" isPushBackRoute="0" name=""  />
        <arc begin="132" end="137" isPushBackRoute="0" name=""  />
        <arc begin="0" end="226" isPushBackRoute="1" name="32_(Terminal_Apron)"  />
        <arc begin="226" end="0" isPushBackRoute="1" name="32_(Terminal_Apron)"  />
        <arc begin="226" end="98" isPushBackRoute="1" name="32_(Terminal_Apron)"  />
        <arc begin="98" end="226" isPushBackRoute="1" name="32_(Terminal_Apron)"  />
        <arc begin="1" end="227" isPushBackRoute="1" name="31_(Terminal_Apron)"  />
        <arc begin="227" end="1" isPushBackRoute="1" name="31_(Terminal_Apron)"  />
        <arc begin="227" end="101" isPushBackRoute="1" name="31_(Terminal_Apron)"  />
        <arc begin="101" end="227" isPushBackRoute="1" name="31_(Terminal_Apron)"  />
        <arc begin="2" end="228" isPushBackRoute="1" name="29_(Terminal_Apron)"  />
        <arc begin="228" end="2" isPushBackRoute="1" name="29_(Terminal_Apron)"  />
        <arc begin="228" end="155" isPushBackRoute="1" name="29_(Terminal_Apron)"  />
        <arc begin="155" end="228" isPushBackRoute="1" name="29_(Terminal_Apron)"  />
        <arc begin="3" end="229" isPushBackRoute="1" name="28_(Terminal_Apron)"  />
        <arc begin="229" end="3" isPushBackRoute="1" name="28_(Terminal_Apron)"  />
        <arc begin="229" end="153" isPushBackRoute="1" name="28_(Terminal_Apron)"  />
        <arc begin="153" end="229" isPushBackRoute="1" name="28_(Terminal_Apron)"  />
        <arc begin="4" end="230" isPushBackRoute="1" name="27_(Terminal_Apron)"  />
        <arc begin="230" end="4" isPushBackRoute="1" name="27_(Terminal_Apron)"  />
        <arc begin="230" end="88" isPushBackRoute="1" name="27_(Terminal_Apron)"  />
        <arc begin="88" end="230" isPushBackRoute="1" name="27_(Terminal_Apron)"  />
        <arc begin="5" end="231" isPushBackRoute="1" name="26_(Terminal_Apron)"  />
        <arc begin="231" end="5" isPushBackRoute="1" name="26_(Terminal_Apron)"  />
        <arc begin="231" end="87" isPushBackRoute="1" name="26_(Terminal_Apron)"  />
        <arc begin="87" end="231" isPushBackRoute="1" name="26_(Terminal_Apron)"  />
        <arc begin="6" end="232" isPushBackRoute="1" name="25_(Terminal_Apron)"  />
        <arc begin="232" end="6" isPushBackRoute="1" name="25_(Terminal_Apron)"  />
        <arc begin="232" end="86" isPushBackRoute="1" name="25_(Terminal_Apron)"  />
        <arc begin="86" end="232" isPushBackRoute="1" name="25_(Terminal_Apron)"  />
        <arc begin="7" end="233" isPushBackRoute="1" name="24_(Terminal_Apron)"  />
        <arc begin="233" end="7" isPushBackRoute="1" name="24_(Terminal_Apron)"  />
        <arc begin="233" end="82" isPushBackRoute="1" name="24_(Terminal_Apron)"  />
        <arc begin="82" end="233" isPushBackRoute="1" name="24_(Terminal_Apron)"  />
        <arc begin="8" end="234" isPushBackRoute="1" name="23_(Terminal_Apron)"  />
        <arc begin="234" end="8" isPushBackRoute="1" name="23_(Terminal_Apron)"  />
        <arc begin="234" end="161" isPushBackRoute="1" name="23_(Terminal_Apron)"  />
        <arc begin="161" end="234" isPushBackRoute="1" name="23_(Terminal_Apron)"  />
        <arc begin="9" end="235" isPushBackRoute="1" name="22_(Terminal_Apron)"  />
        <arc begin="235" end="9" isPushBackRoute="1" name="22_(Terminal_Apron)"  />
        <arc begin="235" end="162" isPushBackRoute="1" name="22_(Terminal_Apron)"  />
        <arc begin="162" end="235" isPushBackRoute="1" name="22_(Terminal_Apron)"  />
        <arc begin="10" end="236" isPushBackRoute="1" name="21_(Terminal_Apron)"  />
        <arc begin="236" end="10" isPushBackRoute="1" name="21_(Terminal_Apron)"  />
        <arc begin="236" end="85" isPushBackRoute="1" name="21_(Terminal_Apron)"  />
        <arc begin="85" end="236" isPushBackRoute="1" name="21_(Terminal_Apron)"  />
        <arc begin="11" end="237" isPushBackRoute="1" name="H56_(Heli_Apron)"  />
        <arc begin="237" end="11" isPushBackRoute="1" name="H56_(Heli_Apron)"  />
        <arc begin="237" end="67" isPushBackRoute="1" name="H56_(Heli_Apron)"  />
        <arc begin="67" end="237" isPushBackRoute="1" name="H56_(Heli_Apron)"  />
        <arc begin="12" end="238" isPushBackRoute="1" name="H55_(Heli_Apron)"  />
        <arc begin="238" end="12" isPushBackRoute="1" name="H55_(Heli_Apron)"  />
        <arc begin="238" end="66" isPushBackRoute="1" name="H55_(Heli_Apron)"  />
        <arc begin="66" end="238" isPushBackRoute="1" name="H55_(Heli_Apron)"  />
        <arc begin="13" end="239" isPushBackRoute="1" name="H54_(Heli_Apron)"  />
        <arc begin="239" end="13" isPushBackRoute="1" name="H54_(Heli_Apron)"  />
        <arc begin="239" end="65" isPushBackRoute="1" name="H54_(Heli_Apron)"  />
        <arc begin="65" end="239" isPushBackRoute="1" name="H54_(Heli_Apron)"  />
        <arc begin="14" end="240" isPushBackRoute="1" name="H53_(Heli_Apron)"  />
        <arc begin="240" end="14" isPushBackRoute="1" name="H53_(Heli_Apron)"  />
        <arc begin="240" end="64" isPushBackRoute="1" name="H53_(Heli_Apron)"  />
        <arc begin="64" end="240" isPushBackRoute="1" name="H53_(Heli_Apron)"  />
        <arc begin="15" end="241" isPushBackRoute="1" name="H52_(Heli_Apron)"  />
        <arc begin="241" end="15" isPushBackRoute="1" name="H52_(Heli_Apron)"  />
        <arc begin="241" end="63" isPushBackRoute="1" name="H52_(Heli_Apron)"  />
        <arc begin="63" end="241" isPushBackRoute="1" name="H52_(Heli_Apron)"  />
        <arc begin="16" end="242" isPushBackRoute="1" name="H51_(Heli_Apron)"  />
        <arc begin="242" end="16" isPushBackRoute="1" name="H51_(Heli_Apron)"  />
        <arc begin="242" end="62" isPushBackRoute="1" name="H51_(Heli_Apron)"  />
        <arc begin="62" end="242" isPushBackRoute="1" name="H51_(Heli_Apron)"  />
        <arc begin="17" end="243" isPushBackRoute="1" name="H50_(Heli_Apron)"  />
        <arc begin="243" end="17" isPushBackRoute="1" name="H50_(Heli_Apron)"  />
        <arc begin="243" end="96" isPushBackRoute="1" name="H50_(Heli_Apron)"  />
        <arc begin="96" end="243" isPushBackRoute="1" name="H50_(Heli_Apron)"  />
        <arc begin="18" end="244" isPushBackRoute="1" name="48_(Apron_N)"  />
        <arc begin="244" end="18" isPushBackRoute="1" name="48_(Apron_N)"  />
        <arc begin="244" end="152" isPushBackRoute="1" name="48_(Apron_N)"  />
        <arc begin="152" end="244" isPushBackRoute="1" name="48_(Apron_N)"  />
        <arc begin="19" end="245" isPushBackRoute="1" name="47_(Apron_N)"  />
        <arc begin="245" end="19" isPushBackRoute="1" name="47_(Apron_N)"  />
        <arc begin="245" end="153" isPushBackRoute="1" name="47_(Apron_N)"  />
        <arc begin="153" end="245" isPushBackRoute="1" name="47_(Apron_N)"  />
        <arc begin="20" end="246" isPushBackRoute="1" name="46_(Apron_N)"  />
        <arc begin="246" end="20" isPushBackRoute="1" name="46_(Apron_N)"  />
        <arc begin="246" end="155" isPushBackRoute="1" name="46_(Apron_N)"  />
        <arc begin="155" end="246" isPushBackRoute="1" name="46_(Apron_N)"  />
        <arc begin="21" end="247" isPushBackRoute="1" name="43_(Apron_N)"  />
        <arc begin="247" end="21" isPushBackRoute="1" name="43_(Apron_N)"  />
        <arc begin="247" end="101" isPushBackRoute="1" name="43_(Apron_N)"  />
        <arc begin="101" end="247" isPushBackRoute="1" name="43_(Apron_N)"  />
        <arc begin="22" end="248" isPushBackRoute="1" name="42_(Apron_N)"  />
        <arc begin="248" end="22" isPushBackRoute="1" name="42_(Apron_N)"  />
        <arc begin="248" end="92" isPushBackRoute="1" name="42_(Apron_N)"  />
        <arc begin="92" end="248" isPushBackRoute="1" name="42_(Apron_N)"  />
        <arc begin="23" end="249" isPushBackRoute="1" name="8_(Remote_Apron_S)"  />
        <arc begin="249" end="23" isPushBackRoute="1" name="8_(Remote_Apron_S)"  />
        <arc begin="249" end="79" isPushBackRoute="1" name="8_(Remote_Apron_S)"  />
        <arc begin="79" end="249" isPushBackRoute="1" name="8_(Remote_Apron_S)"  />
        <arc begin="24" end="250" isPushBackRoute="1" name="7_(Remote_Apron_S)"  />
        <arc begin="250" end="24" isPushBackRoute="1" name="7_(Remote_Apron_S)"  />
        <arc begin="250" end="78" isPushBackRoute="1" name="7_(Remote_Apron_S)"  />
        <arc begin="78" end="250" isPushBackRoute="1" name="7_(Remote_Apron_S)"  />
        <arc begin="25" end="251" isPushBackRoute="1" name="6_(Remote_Apron_S)"  />
        <arc begin="251" end="25" isPushBackRoute="1" name="6_(Remote_Apron_S)"  />
        <arc begin="251" end="77" isPushBackRoute="1" name="6_(Remote_Apron_S)"  />
        <arc begin="77" end="251" isPushBackRoute="1" name="6_(Remote_Apron_S)"  />
        <arc begin="26" end="252" isPushBackRoute="1" name="5_(Remote_Apron_S)"  />
        <arc begin="252" end="26" isPushBackRoute="1" name="5_(Remote_Apron_S)"  />
        <arc begin="252" end="167" isPushBackRoute="1" name="5_(Remote_Apron_S)"  />
        <arc begin="167" end="252" isPushBackRoute="1" name="5_(Remote_Apron_S)"  />
        <arc begin="27" end="253" isPushBackRoute="1" name="4_(Remote_Apron_S)"  />
        <arc begin="253" end="27" isPushBackRoute="1" name="4_(Remote_Apron_S)"  />
        <arc begin="253" end="168" isPushBackRoute="1" name="4_(Remote_Apron_S)"  />
        <arc begin="168" end="253" isPushBackRoute="1" name="4_(Remote_Apron_S)"  />
        <arc begin="28" end="254" isPushBackRoute="1" name="3_(Remote_Apron_S)"  />
        <arc begin="254" end="28" isPushBackRoute="1" name="3_(Remote_Apron_S)"  />
        <arc begin="254" end="169" isPushBackRoute="1" name="3_(Remote_Apron_S)"  />
        <arc begin="169" end="254" isPushBackRoute="1" name="3_(Remote_Apron_S)"  />
        <arc begin="29" end="255" isPushBackRoute="1" name="2_(Remote_Apron_S)"  />
        <arc begin="255" end="29" isPushBackRoute="1" name="2_(Remote_Apron_S)"  />
        <arc begin="255" end="71" isPushBackRoute="1" name="2_(Remote_Apron_S)"  />
        <arc begin="71" end="255" isPushBackRoute="1" name="2_(Remote_Apron_S)"  />
        <arc begin="30" end="256" isPushBackRoute="1" name="1L_(Remote_Apron_S)"  />
        <arc begin="256" end="30" isPushBackRoute="1" name="1L_(Remote_Apron_S)"  />
        <arc begin="256" end="73" isPushBackRoute="1" name="1L_(Remote_Apron_S)"  />
        <arc begin="73" end="256" isPushBackRoute="1" name="1L_(Remote_Apron_S)"  />
        <arc begin="31" end="257" isPushBackRoute="1" name="1R_(Remote_Apron_S)"  />
        <arc begin="257" end="31" isPushBackRoute="1" name="1R_(Remote_Apron_S)"  />
        <arc begin="257" end="70" isPushBackRoute="1" name="1R_(Remote_Apron_S)"  />
        <arc begin="70" end="257" isPushBackRoute="1" name="1R_(Remote_Apron_S)"  />
        <arc begin="32" end="258" isPushBackRoute="1" name="1_(Remote_Apron_S)"  />
        <arc begin="258" end="32" isPushBackRoute="1" name="1_(Remote_Apron_S)"  />
        <arc begin="258" end="72" isPushBackRoute="1" name="1_(Remote_Apron_S)"  />
        <arc begin="72" end="258" isPushBackRoute="1" name="1_(Remote_Apron_S)"  />
        <arc begin="33" end="259" isPushBackRoute="1" name="60_(Hangar)"  />
        <arc begin="259" end="33" isPushBackRoute="1" name="60_(Hangar)"  />
        <arc begin="259" end="104" isPushBackRoute="1" name="60_(Hangar)"  />
        <arc begin="104" end="259" isPushBackRoute="1" name="60_(Hangar)"  />
        <arc begin="34" end="260" isPushBackRoute="1" name="GA_14_(Remote_Apron_N)"  />
        <arc begin="260" end="34" isPushBackRoute="1" name="GA_14_(Remote_Apron_N)"  />
        <arc begin="260" end="102" isPushBackRoute="1" name="GA_14_(Remote_Apron_N)"  />
        <arc begin="102" end="260" isPushBackRoute="1" name="GA_14_(Remote_Apron_N)"  />
        <arc begin="35" end="261" isPushBackRoute="1" name="GA_13_(Remote_Apron_N)"  />
        <arc begin="261" end="35" isPushBackRoute="1" name="GA_13_(Remote_Apron_N)"  />
        <arc begin="261" end="102" isPushBackRoute="1" name="GA_13_(Remote_Apron_N)"  />
        <arc begin="102" end="261" isPushBackRoute="1" name="GA_13_(Remote_Apron_N)"  />
        <arc begin="36" end="262" isPushBackRoute="1" name="GA_12_(Remote_Apron_N)"  />
        <arc begin="262" end="36" isPushBackRoute="1" name="GA_12_(Remote_Apron_N)"  />
        <arc begin="262" end="120" isPushBackRoute="1" name="GA_12_(Remote_Apron_N)"  />
        <arc begin="120" end="262" isPushBackRoute="1" name="GA_12_(Remote_Apron_N)"  />
        <arc begin="37" end="263" isPushBackRoute="1" name="GA_11_(Remote_Apron_N)"  />
        <arc begin="263" end="37" isPushBackRoute="1" name="GA_11_(Remote_Apron_N)"  />
        <arc begin="263" end="103" isPushBackRoute="1" name="GA_11_(Remote_Apron_N)"  />
        <arc begin="103" end="263" isPushBackRoute="1" name="GA_11_(Remote_Apron_N)"  />
        <arc begin="38" end="264" isPushBackRoute="1" name="GA_10_(Remote_Apron_N)"  />
        <arc begin="264" end="38" isPushBackRoute="1" name="GA_10_(Remote_Apron_N)"  />
        <arc begin="264" end="103" isPushBackRoute="1" name="GA_10_(Remote_Apron_N)"  />
        <arc begin="103" end="264" isPushBackRoute="1" name="GA_10_(Remote_Apron_N)"  />
        <arc begin="39" end="265" isPushBackRoute="1" name="GA_9_(Remote_Apron_N)"  />
        <arc begin="265" end="39" isPushBackRoute="1" name="GA_9_(Remote_Apron_N)"  />
        <arc begin="265" end="116" isPushBackRoute="1" name="GA_9_(Remote_Apron_N)"  />
        <arc begin="116" end="265" isPushBackRoute="1" name="GA_9_(Remote_Apron_N)"  />
        <arc begin="40" end="266" isPushBackRoute="1" name="GA_8_(Remote_Apron_N)"  />
        <arc begin="266" end="40" isPushBackRoute="1" name="GA_8_(Remote_Apron_N)"  />
        <arc begin="266" end="114" isPushBackRoute="1" name="GA_8_(Remote_Apron_N)"  />
        <arc begin="114" end="266" isPushBackRoute="1" name="GA_8_(Remote_Apron_N)"  />
        <arc begin="41" end="267" isPushBackRoute="1" name="GA_7_(Remote_Apron_N)"  />
        <arc begin="267" end="41" isPushBackRoute="1" name="GA_7_(Remote_Apron_N)"  />
        <arc begin="267" end="115" isPushBackRoute="1" name="GA_7_(Remote_Apron_N)"  />
        <arc begin="115" end="267" isPushBackRoute="1" name="GA_7_(Remote_Apron_N)"  />
        <arc begin="42" end="268" isPushBackRoute="1" name="GA_6_(Remote_Apron_N)"  />
        <arc begin="268" end="42" isPushBackRoute="1" name="GA_6_(Remote_Apron_N)"  />
        <arc begin="268" end="115" isPushBackRoute="1" name="GA_6_(Remote_Apron_N)"  />
        <arc begin="115" end="268" isPushBackRoute="1" name="GA_6_(Remote_Apron_N)"  />
        <arc begin="43" end="269" isPushBackRoute="1" name="GA_5_(Remote_Apron_N)"  />
        <arc begin="269" end="43" isPushBackRoute="1" name="GA_5_(Remote_Apron_N)"  />
        <arc begin="269" end="122" isPushBackRoute="1" name="GA_5_(Remote_Apron_N)"  />
        <arc begin="122" end="269" isPushBackRoute="1" name="GA_5_(Remote_Apron_N)"  />
        <arc begin="44" end="270" isPushBackRoute="1" name="GA_4_(Remote_Apron_N)"  />
        <arc begin="270" end="44" isPushBackRoute="1" name="GA_4_(Remote_Apron_N)"  />
        <arc begin="270" end="116" isPushBackRoute="1" name="GA_4_(Remote_Apron_N)"  />
        <arc begin="116" end="270" isPushBackRoute="1" name="GA_4_(Remote_Apron_N)"  />
        <arc begin="45" end="271" isPushBackRoute="1" name="GA_3_(Remote_Apron_N)"  />
        <arc begin="271" end="45" isPushBackRoute="1" name="GA_3_(Remote_Apron_N)"  />
        <arc begin="271" end="103" isPushBackRoute="1" name="GA_3_(Remote_Apron_N)"  />
        <arc begin="103" end="271" isPushBackRoute="1" name="GA_3_(Remote_Apron_N)"  />
        <arc begin="46" end="272" isPushBackRoute="1" name="GA_2_(Remote_Apron_N)"  />
        <arc begin="272" end="46" isPushBackRoute="1" name="GA_2_(Remote_Apron_N)"  />
        <arc begin="272" end="123" isPushBackRoute="1" name="GA_2_(Remote_Apron_N)"  />
        <arc begin="123" end="272" isPushBackRoute="1" name="GA_2_(Remote_Apron_N)"  />
        <arc begin="47" end="273" isPushBackRoute="1" name="GA_1_(Remote_Apron_N)"  />
        <arc begin="273" end="47" isPushBackRoute="1" name="GA_1_(Remote_Apron_N)"  />
        <arc begin="273" end="103" isPushBackRoute="1" name="GA_1_(Remote_Apron_N)"  />
        <arc begin="103" end="273" isPushBackRoute="1" name="GA_1_(Remote_Apron_N)"  />
        <arc begin="48" end="274" isPushBackRoute="1" name="GA_9_(Technical_Apron)"  />
        <arc begin="274" end="48" isPushBackRoute="1" name="GA_9_(Technical_Apron)"  />
        <arc begin="274" end="110" isPushBackRoute="1" name="GA_9_(Technical_Apron)"  />
        <arc begin="110" end="274" isPushBackRoute="1" name="GA_9_(Technical_Apron)"  />
        <arc begin="49" end="275" isPushBackRoute="1" name="GA_8_(Technical_Apron)"  />
        <arc begin="275" end="49" isPushBackRoute="1" name="GA_8_(Technical_Apron)"  />
        <arc begin="275" end="110" isPushBackRoute="1" name="GA_8_(Technical_Apron)"  />
        <arc begin="110" end="275" isPushBackRoute="1" name="GA_8_(Technical_Apron)"  />
        <arc begin="50" end="276" isPushBackRoute="1" name="GA_7_(Technical_Apron)"  />
        <arc begin="276" end="50" isPushBackRoute="1" name="GA_7_(Technical_Apron)"  />
        <arc begin="276" end="110" isPushBackRoute="1" name="GA_7_(Technical_Apron)"  />
        <arc begin="110" end="276" isPushBackRoute="1" name="GA_7_(Technical_Apron)"  />
        <arc begin="51" end="277" isPushBackRoute="1" name="GA_6_(Technical_Apron)"  />
        <arc begin="277" end="51" isPushBackRoute="1" name="GA_6_(Technical_Apron)"  />
        <arc begin="277" end="110" isPushBackRoute="1" name="GA_6_(Technical_Apron)"  />
        <arc begin="110" end="277" isPushBackRoute="1" name="GA_6_(Technical_Apron)"  />
        <arc begin="52" end="278" isPushBackRoute="1" name="GA_5_(Technical_Apron)"  />
        <arc begin="278" end="52" isPushBackRoute="1" name="GA_5_(Technical_Apron)"  />
        <arc begin="278" end="110" isPushBackRoute="1" name="GA_5_(Technical_Apron)"  />
        <arc begin="110" end="278" isPushBackRoute="1" name="GA_5_(Technical_Apron)"  />
        <arc begin="53" end="279" isPushBackRoute="1" name="GA_4_(Technical_Apron)"  />
        <arc begin="279" end="53" isPushBackRoute="1" name="GA_4_(Technical_Apron)"  />
        <arc begin="279" end="111" isPushBackRoute="1" name="GA_4_(Technical_Apron)"  />
        <arc begin="111" end="279" isPushBackRoute="1" name="GA_4_(Technical_Apron)"  />
        <arc begin="54" end="280" isPushBackRoute="1" name="GA_3_(Technical_Apron)"  />
        <arc begin="280" end="54" isPushBackRoute="1" name="GA_3_(Technical_Apron)"  />
        <arc begin="280" end="112" isPushBackRoute="1" name="GA_3_(Technical_Apron)"  />
        <arc begin="112" end="280" isPushBackRoute="1" name="GA_3_(Technical_Apron)"  />
        <arc begin="55" end="281" isPushBackRoute="1" name="GA_2_(Technical_Apron)"  />
        <arc begin="281" end="55" isPushBackRoute="1" name="GA_2_(Technical_Apron)"  />
        <arc begin="281" end="112" isPushBackRoute="1" name="GA_2_(Technical_Apron)"  />
        <arc begin="112" end="281" isPushBackRoute="1" name="GA_2_(Technical_Apron)"  />
        <arc begin="56" end="282" isPushBackRoute="1" name="GA_1_(Technical_Apron)"  />
        <arc begin="282" end="56" isPushBackRoute="1" name="GA_1_(Technical_Apron)"  />
        <arc begin="282" end="112" isPushBackRoute="1" name="GA_1_(Technical_Apron)"  />
        <arc begin="112" end="282" isPushBackRoute="1" name="GA_1_(Technical_Apron)"  />
        <arc begin="57" end="283" isPushBackRoute="1" name="GA_0_(Technical_Apron)"  />
        <arc begin="283" end="57" isPushBackRoute="1" name="GA_0_(Technical_Apron)"  />
        <arc begin="283" end="111" isPushBackRoute="1" name="GA_0_(Technical_Apron)"  />
        <arc begin="111" end="283" isPushBackRoute="1" name="GA_0_(Technical_Apron)"  />
        <arc begin="58" end="284" isPushBackRoute="1" name="PAD_4_(DE-ICE)"  />
        <arc begin="284" end="58" isPushBackRoute="1" name="PAD_4_(DE-ICE)"  />
        <arc begin="284" end="137" isPushBackRoute="1" name="PAD_4_(DE-ICE)"  />
        <arc begin="137" end="284" isPushBackRoute="1" name="PAD_4_(DE-ICE)"  />
        <arc begin="59" end="285" isPushBackRoute="1" name="PAD_3_(DE-ICE)"  />
        <arc begin="285" end="59" isPushBackRoute="1" name="PAD_3_(DE-ICE)"  />
        <arc begin="285" end="139" isPushBackRoute="1" name="PAD_3_(DE-ICE)"  />
        <arc begin="139" end="285" isPushBackRoute="1" name="PAD_3_(DE-ICE)"  />
        <arc begin="60" end="286" isPushBackRoute="1" name="PAD_2_(DE-ICE)"  />
        <arc begin="286" end="60" isPushBackRoute="1" name="PAD_2_(DE-ICE)"  />
        <arc begin="286" end="139" isPushBackRoute="1" name="PAD_2_(DE-ICE)"  />
        <arc begin="139" end="286" isPushBackRoute="1" name="PAD_2_(DE-ICE)"  />
        <arc begin="61" end="287" isPushBackRoute="1" name="PAD_1_(DE-ICE)"  />
        <arc begin="287" end="61" isPushBackRoute="1" name="PAD_1_(DE-ICE)"  />
        <arc begin="287" end="140" isPushBackRoute="1" name="PAD_1_(DE-ICE)"  />
        <arc begin="140" end="287" isPushBackRoute="1" name="PAD_1_(DE-ICE)"  />
 </TaxiWaySegments>
</groundnet>
