<?xml version="1.0"?>
<groundnet>
  <version>1</version>
  <parkingList>
        <Parking index="0" type="gate" name="Depart_C1" lat="N43 28.252889" lon="W1 31.938482" heading="0"  radius="44" pushBackRoute="None" airlineCodes="" />
        <Parking index="1" type="gate" name="Depart_C7" lat="N43 28.275586" lon="W1 31.740425" heading="0"  radius="44" pushBackRoute="None" airlineCodes="" />
        <Parking index="2" type="gate" name="Depart_Parking_Sud" lat="N43 27.959975" lon="W1 32.042404" heading="145.04"  radius="44" pushBackRoute="None" airlineCodes="" />
        <Parking index="3" type="gate" name="Depart_Zone_A_(Aviation_Generale)" lat="N43 28.234175" lon="W1 32.093621" heading="91.8"  radius="44" pushBackRoute="None" airlineCodes="" />
        <Parking index="4" type="gate" name="Depart_zone_B_(Aviation_Generale)" lat="N43 28.237981" lon="W1 31.699649" heading="272.32"  radius="44" pushBackRoute="None" airlineCodes="" />
 </parkingList>
</groundnet>
