<?xml version="1.0"?>
<groundnet>
  <version>1</version>
  <parkingList>
        <Parking index="0" type="gate" name="Ramp_Start_West_tarmac" lat="N42 37.093050" lon="W82 50.731552" heading="91.93"  radius="36" pushBackRoute="12" airlineCodes="" />
        <Parking index="1" type="gate" name="Ramp_Start_East_tarmac" lat="N42 36.283714" lon="W82 49.142028" heading="-0.15"  radius="36" pushBackRoute="6" airlineCodes="" />
 </parkingList>
 <TaxiNodes>
        <node index="2" lat="N42 37.550789" lon="W82 49.981014" isOnRunway="0" holdPointType="none"  />
        <node index="3" lat="N42 37.575003" lon="W82 50.077224" isOnRunway="0" holdPointType="none"  />
        <node index="4" lat="N42 35.896141" lon="W82 49.222713" isOnRunway="0" holdPointType="none"  />
        <node index="5" lat="N42 35.911176" lon="W82 50.246459" isOnRunway="0" holdPointType="none"  />
        <node index="6" lat="N42 36.331484" lon="W82 49.215642" isOnRunway="0" holdPointType="PushBack"  />
        <node index="7" lat="N42 36.338173" lon="W82 49.367737" isOnRunway="0" holdPointType="none"  />
        <node index="8" lat="N42 37.054600" lon="W82 49.846314" isOnRunway="0" holdPointType="none"  />
        <node index="9" lat="N42 37.121564" lon="W82 50.204751" isOnRunway="1" holdPointType="none"  />
        <node index="10" lat="N42 37.063041" lon="W82 50.207075" isOnRunway="1" holdPointType="none"  />
        <node index="11" lat="N42 36.509603" lon="W82 50.226281" isOnRunway="1" holdPointType="none"  />
        <node index="12" lat="N42 37.076519" lon="W82 50.584925" isOnRunway="0" holdPointType="PushBack"  />
        <node index="13" lat="N42 37.715171" lon="W82 50.472700" isOnRunway="0" holdPointType="none"  />
        <node index="14" lat="N42 37.752214" lon="W82 50.328576" isOnRunway="0" holdPointType="none"  />
        <node index="15" lat="N42 37.720081" lon="W82 50.183735" isOnRunway="0" holdPointType="none"  />
        <node index="16" lat="N42 35.919473" lon="W82 50.530843" isOnRunway="0" holdPointType="none"  />
        <node index="17" lat="N42 36.515876" lon="W82 50.510414" isOnRunway="0" holdPointType="none"  />
        <node index="18" lat="N42 37.072921" lon="W82 50.492802" isOnRunway="0" holdPointType="none"  />
        <node index="19" lat="N42 36.097282" lon="W82 50.240443" isOnRunway="1" holdPointType="none"  />
        <node index="20" lat="N42 37.572036" lon="W82 50.189096" isOnRunway="1" holdPointType="none"  />
        <node index="21" lat="N42 37.561888" lon="W82 50.189528" isOnRunway="1" holdPointType="none"  />
        <node index="22" lat="N42 37.080281" lon="W82 49.978555" isOnRunway="0" holdPointType="none"  />
        <node index="23" lat="N42 37.093964" lon="W82 50.758661" isOnRunway="0" holdPointType="none"  />
        <node index="24" lat="N42 36.256589" lon="W82 49.141957" isOnRunway="0" holdPointType="none"  />
 </TaxiNodes>
 <TaxiWaySegments>
        <arc begin="11" end="17" isPushBackRoute="0" name="N"  />
        <arc begin="17" end="11" isPushBackRoute="0" name="N"  />
        <arc begin="2" end="3" isPushBackRoute="0" name="N"  />
        <arc begin="3" end="2" isPushBackRoute="0" name="N"  />
        <arc begin="3" end="21" isPushBackRoute="0" name="N"  />
        <arc begin="21" end="3" isPushBackRoute="0" name="N"  />
        <arc begin="22" end="2" isPushBackRoute="0" name="N"  />
        <arc begin="2" end="22" isPushBackRoute="0" name="N"  />
        <arc begin="4" end="5" isPushBackRoute="0" name="N"  />
        <arc begin="5" end="4" isPushBackRoute="0" name="N"  />
        <arc begin="5" end="19" isPushBackRoute="0" name="N"  />
        <arc begin="19" end="5" isPushBackRoute="0" name="N"  />
        <arc begin="6" end="4" isPushBackRoute="0" name="N"  />
        <arc begin="4" end="6" isPushBackRoute="0" name="N"  />
        <arc begin="7" end="6" isPushBackRoute="0" name="N"  />
        <arc begin="6" end="7" isPushBackRoute="0" name="N"  />
        <arc begin="8" end="7" isPushBackRoute="0" name="N"  />
        <arc begin="7" end="8" isPushBackRoute="0" name="N"  />
        <arc begin="9" end="22" isPushBackRoute="0" name="N"  />
        <arc begin="22" end="9" isPushBackRoute="0" name="N"  />
        <arc begin="22" end="8" isPushBackRoute="0" name="N"  />
        <arc begin="8" end="22" isPushBackRoute="0" name="N"  />
        <arc begin="10" end="9" isPushBackRoute="0" name="N"  />
        <arc begin="9" end="10" isPushBackRoute="0" name="N"  />
        <arc begin="18" end="10" isPushBackRoute="0" name="N"  />
        <arc begin="10" end="18" isPushBackRoute="0" name="N"  />
        <arc begin="12" end="18" isPushBackRoute="0" name="N"  />
        <arc begin="18" end="12" isPushBackRoute="0" name="N"  />
        <arc begin="13" end="14" isPushBackRoute="0" name="N"  />
        <arc begin="14" end="13" isPushBackRoute="0" name="N"  />
        <arc begin="14" end="15" isPushBackRoute="0" name="N"  />
        <arc begin="15" end="14" isPushBackRoute="0" name="N"  />
        <arc begin="15" end="20" isPushBackRoute="0" name="N"  />
        <arc begin="20" end="15" isPushBackRoute="0" name="N"  />
        <arc begin="16" end="17" isPushBackRoute="0" name="N"  />
        <arc begin="17" end="16" isPushBackRoute="0" name="N"  />
        <arc begin="17" end="18" isPushBackRoute="0" name="N"  />
        <arc begin="18" end="17" isPushBackRoute="0" name="N"  />
        <arc begin="18" end="13" isPushBackRoute="0" name="N"  />
        <arc begin="13" end="18" isPushBackRoute="0" name="N"  />
        <arc begin="19" end="5" isPushBackRoute="0" name="N"  />
        <arc begin="5" end="19" isPushBackRoute="0" name="N"  />
        <arc begin="5" end="16" isPushBackRoute="0" name="N"  />
        <arc begin="16" end="5" isPushBackRoute="0" name="N"  />
        <arc begin="0" end="23" isPushBackRoute="1" name="Ramp_Start_West_tarmac"  />
        <arc begin="23" end="0" isPushBackRoute="1" name="Ramp_Start_West_tarmac"  />
        <arc begin="23" end="12" isPushBackRoute="1" name="Ramp_Start_West_tarmac"  />
        <arc begin="12" end="23" isPushBackRoute="1" name="Ramp_Start_West_tarmac"  />
        <arc begin="1" end="24" isPushBackRoute="1" name="Ramp_Start_East_tarmac"  />
        <arc begin="24" end="1" isPushBackRoute="1" name="Ramp_Start_East_tarmac"  />
        <arc begin="24" end="6" isPushBackRoute="1" name="Ramp_Start_East_tarmac"  />
        <arc begin="6" end="24" isPushBackRoute="1" name="Ramp_Start_East_tarmac"  />
 </TaxiWaySegments>
</groundnet>
