<?xml version='1.0' encoding='ISO-8859-1'?>
<PropertyList>
  <runway>
    <threshold>
      <lon>-72.21577564</lon>
      <lat>42.28472564</lat>
      <rwy>18</rwy>
      <hdg-deg>165.00</hdg-deg>
      <displ-m>0.0</displ-m>
      <stopw-m>0.0</stopw-m>
    </threshold>
    <threshold>
      <lon>-72.2138277</lon>
      <lat>42.27934712</lat>
      <rwy>36</rwy>
      <hdg-deg>345.00</hdg-deg>
      <displ-m>0.0</displ-m>
      <stopw-m>0.0</stopw-m>
    </threshold>
  </runway>
</PropertyList>
