<?xml version="1.0"?>
<PropertyList>
<jetway n="0">
  <model type="string">generic</model>
  <gate type="string">0</gate>
  <door type="int">0</door>
  <airline type="string">FGFS</airline>
  <latitude-deg type="double">43.5378866</latitude-deg>
  <longitude-deg type="double">-84.082392902</longitude-deg>
  <elevation-m type="double">200.292</elevation-m>
  <heading-deg type="double">257.299988</heading-deg>
  <initial-position>
    <jetway-extension-m type="double">0</jetway-extension-m>
    <jetway-heading-deg type="double">0</jetway-heading-deg>
    <jetway-pitch-deg type="double">0</jetway-pitch-deg>
    <entrance-heading-deg type="double">0</entrance-heading-deg>
  </initial-position>
</jetway>
<jetway n="1">
  <model type="string">generic</model>
  <gate type="string">1</gate>
  <door type="int">0</door>
  <airline type="string">FGFS</airline>
  <latitude-deg type="double">43.537672315</latitude-deg>
  <longitude-deg type="double">-84.082088095</longitude-deg>
  <elevation-m type="double">200.266</elevation-m>
  <heading-deg type="double">24.639999</heading-deg>
  <initial-position>
    <jetway-extension-m type="double">0</jetway-extension-m>
    <jetway-heading-deg type="double">0</jetway-heading-deg>
    <jetway-pitch-deg type="double">0</jetway-pitch-deg>
    <entrance-heading-deg type="double">0</entrance-heading-deg>
  </initial-position>
</jetway>
<jetway n="2">
  <model type="string">generic</model>
  <gate type="string">2</gate>
  <door type="int">0</door>
  <airline type="string">FGFS</airline>
  <latitude-deg type="double">43.534043914</latitude-deg>
  <longitude-deg type="double">-84.089500951</longitude-deg>
  <elevation-m type="double">202.289</elevation-m>
  <heading-deg type="double">168.509998</heading-deg>
  <initial-position>
    <jetway-extension-m type="double">0</jetway-extension-m>
    <jetway-heading-deg type="double">0</jetway-heading-deg>
    <jetway-pitch-deg type="double">0</jetway-pitch-deg>
    <entrance-heading-deg type="double">0</entrance-heading-deg>
  </initial-position>
</jetway>
<jetway n="3">
  <model type="string">generic</model>
  <gate type="string">3</gate>
  <door type="int">0</door>
  <airline type="string">FGFS</airline>
  <latitude-deg type="double">43.534081307</latitude-deg>
  <longitude-deg type="double">-84.089963348</longitude-deg>
  <elevation-m type="double">202.364</elevation-m>
  <heading-deg type="double">197.68</heading-deg>
  <initial-position>
    <jetway-extension-m type="double">0</jetway-extension-m>
    <jetway-heading-deg type="double">0</jetway-heading-deg>
    <jetway-pitch-deg type="double">0</jetway-pitch-deg>
    <entrance-heading-deg type="double">0</entrance-heading-deg>
  </initial-position>
</jetway>
<jetway n="4">
  <model type="string">generic</model>
  <gate type="string">4</gate>
  <door type="int">0</door>
  <airline type="string">FGFS</airline>
  <latitude-deg type="double">43.533734162</latitude-deg>
  <longitude-deg type="double">-84.089488107</longitude-deg>
  <elevation-m type="double">202.32</elevation-m>
  <heading-deg type="double">72.229996</heading-deg>
  <initial-position>
    <jetway-extension-m type="double">0</jetway-extension-m>
    <jetway-heading-deg type="double">0</jetway-heading-deg>
    <jetway-pitch-deg type="double">0</jetway-pitch-deg>
    <entrance-heading-deg type="double">0</entrance-heading-deg>
  </initial-position>
</jetway>
<jetway n="5">
  <model type="string">generic</model>
  <gate type="string">5</gate>
  <door type="int">0</door>
  <airline type="string">FGFS</airline>
  <latitude-deg type="double">43.537709851</latitude-deg>
  <longitude-deg type="double">-84.082375706</longitude-deg>
  <elevation-m type="double">200.326</elevation-m>
  <heading-deg type="double">291.830017</heading-deg>
  <initial-position>
    <jetway-extension-m type="double">0</jetway-extension-m>
    <jetway-heading-deg type="double">0</jetway-heading-deg>
    <jetway-pitch-deg type="double">0</jetway-pitch-deg>
    <entrance-heading-deg type="double">0</entrance-heading-deg>
  </initial-position>
</jetway>
</PropertyList>
