<?xml version="1.0"?>
<groundnet>
  <version>1</version>
  <parkingList>
        <Parking index="0" type="gate" name="Terminal_start" lat="N33 21.238957" lon="W110 39.817556" heading="101.04"  radius="32" airlineCodes="" />
        <Parking index="1" type="gate" name="Hanger_start_1" lat="N33 21.234793" lon="W110 39.761266" heading="251.03"  radius="32" airlineCodes="" />
        <Parking index="2" type="gate" name="Hanger_start_2" lat="N33 21.223647" lon="W110 39.722874" heading="104.89"  radius="32" airlineCodes="" />
        <Parking index="3" type="gate" name="Ramp_parking_1" lat="N33 21.184306" lon="W110 39.669509" heading="11.31"  radius="32" airlineCodes="" />
        <Parking index="4" type="gate" name="Ramp_parking_2" lat="N33 21.221098" lon="W110 39.681705" heading="188.62"  radius="32" airlineCodes="" />
        <Parking index="5" type="ga" name="Helicoptor_spot_start" lat="N33 21.184562" lon="W110 39.591202" heading="-168.88"  radius="32" airlineCodes="" />
 </parkingList>
</groundnet>
